Workbook

Sheet Portada
B2: LÍNEA DE PRODUCTOS DIGITALES · PLANTILLAS EXCEL
B4: FLUJO DE CAJA PARA NEGOCIOS
B7: Proyecta y registra las entradas y salidas de efectivo de tu negocio mes a mes, y visualiza tu saldo de caja en todo momento — con panel de control, gráficos automáticos y selector de moneda (local / USD).
B10: QUÉ INCLUYE ESTA PLANTILLA
B11: ✔ Dashboard con indicadores clave (KPIs) y gráficos automáticos
B12: ✔ Fórmulas automáticas: nada que calcular a mano
B13: ✔ Gráficos: pastel (egresos por categoría), barras y evolución del saldo de caja
B14: ✔ Resumen dinámico tipo tabla dinámica por categoría y por mes
B15: ✔ Saldo de caja proyectado mes a mes (arrastre automático)
B16: ✔ Listas desplegables y validación de datos en cada registro
B17: ✔ Selector de moneda: local o USD, con tipo de cambio editable
B18: ✔ Hoja de instrucciones paso a paso
... B24: © Tu Marca de Plantillas · www.tumarca.com

Sheet Instrucciones
B2: CÓMO USAR ESTA PLANTILLA
B4: 1. Configuración
B5: Define el símbolo de tu moneda local, el tipo de cambio, el saldo de caja inicial de tu negocio y si la plantilla se muestra en moneda LOCAL o USD.
B7: 2. Categorías
B8: En la hoja 'Categorías' revisa o edita las categorías de ingreso/egreso de efectivo de tu negocio.
B10: 3. Flujo de Caja
B11: En la hoja 'Flujo de Caja' registra, mes a mes, cuánto efectivo entró y salió en cada categoría. La columna 'Total anual' se calcula sola.
B13: 4. Resumen automático
B14: La hoja 'Resumen' calcula tus ingresos y egresos totales por mes, tu flujo neto y tu saldo de caja proyectado (arrastrando el saldo inicial mes a mes), como una tabla dinámica.
B16: 5. Dashboard
B17: La hoja 'Dashboard' muestra tu saldo de caja actual, tu flujo neto y gráficos que se actualizan solos: ingresos vs. egresos por mes, egresos por categoría y la curva de tu saldo de caja.
B19: 6. Cambiar de moneda
... B25: Soporte y otras plantillas de esta línea de productos: www.tumarca.com

Sheet Configuracion
B2: CONFIGURACIÓN Y MONEDA
B4: Parámetro | C4: Valor | D4: Notas
B5: Nombre de moneda local | C5: Soles (PEN) | D5: Solo referencia. Escribe el nombre de tu moneda.
B6: Símbolo de moneda local | C6: S/ | D6: Símbolo que se usará en el Dashboard cuando la vista esté en LOCAL.
B7: Tipo de cambio (1 USD =) | C7: 3.75 | D7: Cuántas unidades de tu moneda local equivalen a 1 USD.
B8: Moneda de visualización | C8: Local | D8: Elige LOCAL o USD. Afecta Resumen y Dashboard.
B9: Saldo de caja inicial | C9: 5000 | D9: Efectivo disponible al comenzar el año (caja + bancos).
B10: Año de análisis | C10: 2026 | D10: Año que se usa como referencia en Flujo de Caja.
B11: Valores calculados (no editar)
B12: Factor de conversión aplicado | C12: =IF(C8="USD",1/C7,1) -> 1 | D12: Vale 1 si vista LOCAL; vale 1/Tipo de cambio si vista USD.
B13: Símbolo de moneda actual | C13: =IF(C8="USD","US$",C6) -> S/ | D13: Símbolo que verás en el Dashboard según la moneda elegida.
B15: Cambia 'Moneda de visualización' entre Local y USD para recalcular automáticamente toda la plantilla.

Sheet Categorias
B2: CATEGORÍAS DE FLUJO DE CAJA
B4: Categoría (ingreso/egreso)
B5: Ventas al contado
B6: Cobros de cuentas por cobrar
B7: Otros ingresos
B8: Compra de mercadería/insumos
B9: Sueldos y planilla
B10: Alquiler
B11: Servicios (luz, agua, internet)
B12: Marketing y publicidad
B13: Impuestos
B14: Mantenimiento y otros gastos
... B17: Estas categorías deben coincidir, en el mismo orden, con las filas de 'Flujo de Caja'.

Sheet Flujo de Caja
A2: FLUJO DE CAJA MENSUAL (por categoría)
A4: Categoría | B4: Ene | C4: Feb | D4: Mar | E4: Abr | F4: May | G4: Jun | H4: Jul | I4: Ago | J4: Sep | K4: Oct | L4: Nov | M4: Dic | N4: Total anual
A5: =Categorias!$B$5 -> Ventas al contado | B5: 8000 | C5: 8200 | D5: 8500 | E5: 8300 | F5: 8600 | G5: 8700 | H5: 8900 | I5: 8800 | J5: 9000 | K5: 9200 | L5: 9500 | M5: 10500 | N5: =SUM(B5:M5) -> 106200
A6: =Categorias!$B$6 -> Cobros de cuentas por cobrar | B6: 1500 | C6: 1600 | D6: 1400 | E6: 1550 | F6: 1600 | G6: 1650 | H6: 1700 | I6: 1650 | J6: 1800 | K6: 1750 | L6: 1900 | M6: 2000 | N6: =SUM(B6:M6) -> 20100
A7: =Categorias!$B$7 -> Otros ingresos | B7: 200 | C7: 0 | D7: 300 | E7: 0 | F7: 150 | G7: 0 | H7: 0 | I7: 400 | J7: 0 | K7: 0 | L7: 250 | M7: 0 | N7: =SUM(B7:M7) -> 1300
A8: =Categorias!$B$8 -> Compra de mercadería/insumos | B8: 3200 | C8: 3300 | D8: 3400 | E8: 3350 | F8: 3450 | G8: 3500 | H8: 3600 | I8: 3550 | J8: 3650 | K8: 3700 | L8: 3800 | M8: 4200 | N8: =SUM(B8:M8) -> 42700
A9: =Categorias!$B$9 -> Sueldos y planilla | B9: 3500 | C9: 3500 | D9: 3500 | E9: 3500 | F9: 3500 | G9: 3500 | H9: 3500 | I9: 3500 | J9: 3500 | K9: 3500 | L9: 3500 | M9: 4200 | N9: =SUM(B9:M9) -> 42700
A10: =Categorias!$B$10 -> Alquiler | B10: 1200 | C10: 1200 | D10: 1200 | E10: 1200 | F10: 1200 | G10: 1200 | H10: 1200 | I10: 1200 | J10: 1200 | K10: 1200 | L10: 1200 | M10: 1200 | N10: =SUM(B10:M10) -> 14400
A11: =Categorias!$B$11 -> Servicios (luz, agua, internet) | B11: 280 | C11: 290 | D11: 270 | E11: 300 | F11: 310 | G11: 320 | H11: 330 | I11: 310 | J11: 300 | K11: 290 | L11: 300 | M11: 320 | N11: =SUM(B11:M11) -> 3620
A12: =Categorias!$B$12 -> Marketing y publicidad | B12: 400 | C12: 400 | D12: 500 | E12: 400 | F12: 450 | G12: 400 | H12: 500 | I12: 450 | J12: 400 | K12: 500 | L12: 600 | M12: 800 | N12: =SUM(B12:M12) -> 5800
A13: =Categorias!$B$13 -> Impuestos | B13: 600 | C13: 0 | D13: 0 | E13: 600 | F13: 0 | G13: 0 | H13: 600 | I13: 0 | J13: 0 | K13: 600 | L13: 0 | M13: 0 | N13: =SUM(B13:M13) -> 2400
A14: =Categorias!$B$14 -> Mantenimiento y otros gastos | B14: 150 | C14: 100 | D14: 200 | E14: 150 | F14: 100 | G14: 180 | H14: 150 | I14: 120 | J14: 150 | K14: 200 | L14: 180 | M14: 250 | N14: =SUM(B14:M14) -> 1930
A15: =Categorias!$B$15 -> Otros egresos | B15: 100 | C15: 80 | D15: 120 | E15: 90 | F15: 100 | G15: 110 | H15: 90 | I15: 100 | J15: 120 | K15: 100 | L15: 110 | M15: 150 | N15: =SUM(B15:M15) -> 1270
A16: TOTAL | B16: =SUM(B5:B15) -> 19130 | C16: =SUM(C5:C15) -> 18670 | D16: =SUM(D5:D15) -> 19390 | E16: =SUM(E5:E15) -> 19440 | F16: =SUM(F5:F15) -> 19460 | G16: =SUM(G5:G15) -> 19560 | H16: =SUM(H5:H15) -> 20570 | I16: =SUM(I5:I15) -> 20080 | ... N16: =SUM(N5:N15) -> 242420

Sheet Resumen
B2: RESUMEN DINÁMICO (se actualiza solo)
B3: =" Moneda: " & Configuracion!$C$8 -> Moneda: Local
B5: TOTAL ANUAL POR CATEGORÍA
B6: Categoría | C6: Total anual
B7: =Categorias!$B$5 -> Ventas al contado | C7: ='Flujo de Caja'!$N$5*Configuracion!$C$12 -> 106200
B8: =Categorias!$B$6 -> Cobros de cuentas por cobrar | C8: ='Flujo de Caja'!$N$6*Configuracion!$C$12 -> 20100
B9: =Categorias!$B$7 -> Otros ingresos | C9: ='Flujo de Caja'!$N$7*Configuracion!$C$12 -> 1300
B10: =Categorias!$B$8 -> Compra de mercadería/insumos | C10: ='Flujo de Caja'!$N$8*Configuracion!$C$12 -> 42700
B11: =Categorias!$B$9 -> Sueldos y planilla | C11: ='Flujo de Caja'!$N$9*Configuracion!$C$12 -> 42700
B12: =Categorias!$B$10 -> Alquiler | C12: ='Flujo de Caja'!$N$10*Configuracion!$C$12 -> 14400
B13: =Categorias!$B$11 -> Servicios (luz, agua, internet) | C13: ='Flujo de Caja'!$N$11*Configuracion!$C$12 -> 3620
B14: =Categorias!$B$12 -> Marketing y publicidad | C14: ='Flujo de Caja'!$N$12*Configuracion!$C$12 -> 5800
B15: =Categorias!$B$13 -> Impuestos | C15: ='Flujo de Caja'!$N$13*Configuracion!$C$12 -> 2400
B16: =Categorias!$B$14 -> Mantenimiento y otros gastos | C16: ='Flujo de Caja'!$N$14*Configuracion!$C$12 -> 1930
B17: =Categorias!$B$15 -> Otros egresos | C17: ='Flujo de Caja'!$N$15*Configuracion!$C$12 -> 1270
B20: FLUJO DE CAJA MENSUAL Y SALDO PROYECTADO
B21: Mes | C21: Ingresos | D21: Egresos | E21: Flujo neto | F21: Saldo inicial | G21: Saldo final
B22: Enero | C22: =SUM('Flujo de Caja'!B$5:B$7)*Configuracion!$C$12 -> 9700 | D22: =SUM('Flujo de Caja'!B$8:B$15)*Configuracion!$C$12 -> 9430 | E22: =C22-D22 -> 270 | F22: =Configuracion!$C$9*Configuracion!$C$12 -> 5000 | G22: =F22+E22 -> 5270
B23: Febrero | C23: =SUM('Flujo de Caja'!C$5:C$7)*Configuracion!$C$12 -> 9800 | D23: =SUM('Flujo de Caja'!C$8:C$15)*Configuracion!$C$12 -> 8870 | E23: =C23-D23 -> 930 | F23: =G22 -> 5270 | G23: =F23+E23 -> 6200
B24: Marzo | C24: =SUM('Flujo de Caja'!D$5:D$7)*Configuracion!$C$12 -> 10200 | D24: =SUM('Flujo de Caja'!D$8:D$15)*Configuracion!$C$12 -> 9190 | E24: =C24-D24 -> 1010 | F24: =G23 -> 6200 | G24: =F24+E24 -> 7210
B25: Abril | C25: =SUM('Flujo de Caja'!E$5:E$7)*Configuracion!$C$12 -> 9850 | D25: =SUM('Flujo de Caja'!E$8:E$15)*Configuracion!$C$12 -> 9590 | E25: =C25-D25 -> 260 | F25: =G24 -> 7210 | G25: =F25+E25 -> 7470
B26: Mayo | C26: =SUM('Flujo de Caja'!F$5:F$7)*Configuracion!$C$12 -> 10350 | D26: =SUM('Flujo de Caja'!F$8:F$15)*Configuracion!$C$12 -> 9110 | E26: =C26-D26 -> 1240 | F26: =G25 -> 7470 | G26: =F26+E26 -> 8710
B27: Junio | C27: =SUM('Flujo de Caja'!G$5:G$7)*Configuracion!$C$12 -> 10350 | D27: =SUM('Flujo de Caja'!G$8:G$15)*Configuracion!$C$12 -> 9210 | E27: =C27-D27 -> 1140 | F27: =G26 -> 8710 | G27: =F27+E27 -> 9850
B28: Julio | C28: =SUM('Flujo de Caja'!H$5:H$7)*Configuracion!$C$12 -> 10600 | D28: =SUM('Flujo de Caja'!H$8:H$15)*Configuracion!$C$12 -> 9970 | E28: =C28-D28 -> 630 | F28: =G27 -> 9850 | G28: =F28+E28 -> 10480
B29: Agosto | C29: =SUM('Flujo de Caja'!I$5:I$7)*Configuracion!$C$12 -> 10850 | D29: =SUM('Flujo de Caja'!I$8:I$15)*Configuracion!$C$12 -> 9230 | E29: =C29-D29 -> 1620 | F29: =G28 -> 10480 | G29: =F29+E29 -> 12100
B30: Septiembre | C30: =SUM('Flujo de Caja'!J$5:J$7)*Configuracion!$C$12 -> 10800 | D30: =SUM('Flujo de Caja'!J$8:J$15)*Configuracion!$C$12 -> 9320 | E30: =C30-D30 -> 1480 | F30: =G29 -> 12100 | G30: =F30+E30 -> 13580
B31: Octubre | C31: =SUM('Flujo de Caja'!K$5:K$7)*Configuracion!$C$12 -> 10950 | D31: =SUM('Flujo de Caja'!K$8:K$15)*Configuracion!$C$12 -> 10090 | E31: =C31-D31 -> 860 | F31: =G30 -> 13580 | G31: =F31+E31 -> 14440
B32: Noviembre | C32: =SUM('Flujo de Caja'!L$5:L$7)*Configuracion!$C$12 -> 11650 | D32: =SUM('Flujo de Caja'!L$8:L$15)*Configuracion!$C$12 -> 9690 | E32: =C32-D32 -> 1960 | F32: =G31 -> 14440 | G32: =F32+E32 -> 16400
B33: Diciembre | C33: =SUM('Flujo de Caja'!M$5:M$7)*Configuracion!$C$12 -> 12500 | D33: =SUM('Flujo de Caja'!M$8:M$15)*Configuracion!$C$12 -> 11120 | E33: =C33-D33 -> 1380 | F33: =G32 -> 16400 | G33: =F33+E33 -> 17780
B34: TOTAL / SALDO FINAL DEL AÑO | C34: =SUM(C22:C33) -> 127600 | D34: =SUM(D22:D33) -> 114820 | E34: =SUM(E22:E33) -> 12780 | G34: =G33 -> 17780

Sheet Dashboard
B2: DASHBOARD · FLUJO DE CAJA PARA NEGOCIOS
B3: =" Moneda: " & Configuracion!$C$8 & " | Año: " & Configuracion!$C$10 -> Moneda: Local | Año: 2026
B5: SALDO DE CAJA INICIAL | D5: TOTAL INGRESOS (AÑO) | F5: TOTAL EGRESOS (AÑO) | H5: SALDO DE CAJA FINAL
B6: =Configuracion!$C$13&" "&TEXT(Resumen!F22,"#,##0.00") -> S/ 5,000.00 | D6: =Configuracion!$C$13&" "&TEXT(Resumen!C34,"#,##0.00") -> S/ 127,600.00 | F6: =Configuracion!$C$13&" "&TEXT(Resumen!D34,"#,##0.00") -> S/ 114,820.00 | H6: =Configuracion!$C$13&" "&TEXT(Resumen!G34,"#,##0.00") -> S/ 17,780.00
