Workbook

Sheet Portada
B2: LÍNEA DE PRODUCTOS DIGITALES · PLANTILLAS EXCEL
B4: CONTABILIDAD BÁSICA PARA EMPRENDEDORES
B7: Lleva el registro contable de tu negocio sin complicaciones: clasifica cada movimiento con tu plan de cuentas y obtén tu Estado de Resultados (ventas, costos, gastos y utilidad) mes a mes — con panel de control, gráficos automáticos y selector de moneda (local / USD).
B10: QUÉ INCLUYE ESTA PLANTILLA
B11: ✔ Dashboard con indicadores clave (KPIs) y gráficos automáticos
B12: ✔ Fórmulas automáticas: nada que calcular a mano
B13: ✔ Estado de Resultados mensual y anual (ventas, costos, gastos, utilidad)
B14: ✔ Plan de cuentas editable con clasificación por tipo
B15: ✔ Gráficos: pastel (gastos por tipo), barras y evolución de la utilidad neta
B16: ✔ Listas desplegables y validación de datos en cada registro
B17: ✔ Selector de moneda: local o USD, con tipo de cambio editable
B18: ✔ Hoja de instrucciones paso a paso
... B24: © Tu Marca de Plantillas · www.tumarca.com

Sheet Instrucciones
B2: CÓMO USAR ESTA PLANTILLA
B4: 1. Configuración
B5: Define el símbolo de tu moneda local, el tipo de cambio, el año de análisis y si la plantilla se muestra en moneda LOCAL o USD.
B7: 2. Plan de Cuentas
B8: En 'Plan de Cuentas' revisa o edita las cuentas contables de tu negocio y su tipo (Ingreso, Costo de venta, Gasto operativo, Gasto administrativo, Gasto financiero o Impuesto).
B10: 3. Transacciones
B11: En 'Transacciones' registra cada movimiento: fecha, cuenta (lista desplegable), descripción y monto. El tipo de cuenta se completa solo.
B13: 4. Estado de Resultados
B14: La hoja 'Estado de Resultados' calcula automáticamente, mes a mes, tus ventas, costo de venta, utilidad bruta, gastos operativos y administrativos, utilidad operativa, gastos financieros, impuestos y utilidad neta — como un estado de resultados real.
B16: 5. Dashboard
B17: La hoja 'Dashboard' muestra tus ventas, utilidad bruta, utilidad neta y margen neto del año, con gráficos que se actualizan solos.
B19: 6. Cambiar de moneda
... B28: Soporte y otras plantillas de esta línea de productos: www.tumarca.com

Sheet Configuracion
B2: CONFIGURACIÓN Y MONEDA
B4: Parámetro | C4: Valor | D4: Notas
B5: Nombre de moneda local | C5: Soles (PEN) | D5: Solo referencia. Escribe el nombre de tu moneda.
B6: Símbolo de moneda local | C6: S/ | D6: Símbolo que se usará en el Dashboard cuando la vista esté en LOCAL.
B7: Tipo de cambio (1 USD =) | C7: 3.75 | D7: Cuántas unidades de tu moneda local equivalen a 1 USD.
B8: Moneda de visualización | C8: Local | D8: Elige LOCAL o USD. Afecta Estado de Resultados y Dashboard.
B9: Año de análisis | C9: 2026 | D9: Año que se usa como referencia en el Estado de Resultados.
B10: Valores calculados (no editar)
B11: Factor de conversión aplicado | C11: =IF(C8="USD",1/C7,1) -> 1 | D11: Vale 1 si vista LOCAL; vale 1/Tipo de cambio si vista USD.
B12: Símbolo de moneda actual | C12: =IF(C8="USD","US$",C6) -> S/ | D12: Símbolo que verás en el Dashboard según la moneda elegida.
B14: Cambia 'Moneda de visualización' entre Local y USD para recalcular automáticamente toda la plantilla.

Sheet Plan de Cuentas
A2: PLAN DE CUENTAS
A4: Código | B4: Cuenta | C4: Tipo
A5: 4001 | B5: Ventas de productos | C5: Ingreso
A6: 4002 | B6: Ventas de servicios | C6: Ingreso
A7: 5001 | B7: Costo de mercadería vendida | C7: Costo de venta
A8: 6001 | B8: Sueldos y salarios | C8: Gasto operativo
A9: 6002 | B9: Alquiler de local | C9: Gasto operativo
A10: 6003 | B10: Servicios (luz, agua, internet) | C10: Gasto operativo
A11: 6004 | B11: Marketing y publicidad | C11: Gasto administrativo
A12: 6005 | B12: Útiles y suministros de oficina | C12: Gasto administrativo
A13: 7001 | B13: Intereses y comisiones bancarias | C13: Gasto financiero
A14: 8001 | B14: Impuesto a la renta | C14: Impuesto
A16: Puedes renombrar cuentas o agregar filas; el tipo determina en qué línea del Estado de Resultados aparece.

Sheet Transacciones
A2: REGISTRO DE TRANSACCIONES
A3: Completa las columnas A a D para cada movimiento. La columna E (tipo) se calcula automáticamente.
A4: Fecha | B4: Cuenta | C4: Descripción | D4: Monto | E4: Tipo de cuenta
A5: 46027 | B5: Ventas de productos | C5: Ventas de la semana | D5: 4200 | E5: =IF(B5="","",IFERROR(INDEX('Plan de Cuentas'!$C$5:$C$14,MATCH(B5,'Plan de Cuentas'!$B$5:$B$14,0)),"Cuenta no encontrada")) -> Ingreso
A6: 46030 | B6: Costo de mercadería vendida | C6: Costo de productos vendidos | D6: 1800 | E6: =IF(B6="","",IFERROR(INDEX('Plan de Cuentas'!$C$5:$C$14,MATCH(B6,'Plan de Cuentas'!$B$5:$B$14,0)),"Cuenta no encontrada")) -> Costo de venta
A7: 46032 | B7: Sueldos y salarios | C7: Planilla de enero | D7: 1200 | E7: =IF(B7="","",IFERROR(INDEX('Plan de Cuentas'!$C$5:$C$14,MATCH(B7,'Plan de Cuentas'!$B$5:$B$14,0)),"Cuenta no encontrada")) -> Gasto operativo
A8: 46034 | B8: Alquiler de local | C8: Alquiler de enero | D8: 800 | E8: =IF(B8="","",IFERROR(INDEX('Plan de Cuentas'!$C$5:$C$14,MATCH(B8,'Plan de Cuentas'!$B$5:$B$14,0)),"Cuenta no encontrada")) -> Gasto operativo
A9: 46037 | B9: Marketing y publicidad | C9: Campaña en redes sociales | D9: 250 | E9: =IF(B9="","",IFERROR(INDEX('Plan de Cuentas'!$C$5:$C$14,MATCH(B9,'Plan de Cuentas'!$B$5:$B$14,0)),"Cuenta no encontrada")) -> Gasto administrativo
A10: 46042 | B10: Servicios (luz, agua, internet) | C10: Recibos del mes | D10: 180 | E10: =IF(B10="","",IFERROR(INDEX('Plan de Cuentas'!$C$5:$C$14,MATCH(B10,'Plan de Cuentas'!$B$5:$B$14,0)),"Cuenta no encontrada")) -> Gasto operativo
A11: 46050 | B11: Intereses y comisiones bancarias | C11: Comisiones bancarias | D11: 40 | E11: =IF(B11="","",IFERROR(INDEX('Plan de Cuentas'!$C$5:$C$14,MATCH(B11,'Plan de Cuentas'!$B$5:$B$14,0)),"Cuenta no encontrada")) -> Gasto financiero
A12: 46058 | B12: Ventas de productos | C12: Ventas de la semana | D12: 4500 | E12: =IF(B12="","",IFERROR(INDEX('Plan de Cuentas'!$C$5:$C$14,MATCH(B12,'Plan de Cuentas'!$B$5:$B$14,0)),"Cuenta no encontrada")) -> Ingreso
A13: 46059 | B13: Ventas de servicios | C13: Servicio de instalación | D13: 600 | E13: =IF(B13="","",IFERROR(INDEX('Plan de Cuentas'!$C$5:$C$14,MATCH(B13,'Plan de Cuentas'!$B$5:$B$14,0)),"Cuenta no encontrada")) -> Ingreso
A14: 46061 | B14: Costo de mercadería vendida | C14: Costo de productos vendidos | D14: 1900 | E14: =IF(B14="","",IFERROR(INDEX('Plan de Cuentas'!$C$5:$C$14,MATCH(B14,'Plan de Cuentas'!$B$5:$B$14,0)),"Cuenta no encontrada")) -> Costo de venta
A15: 46063 | B15: Sueldos y salarios | C15: Planilla de febrero | D15: 1200 | E15: =IF(B15="","",IFERROR(INDEX('Plan de Cuentas'!$C$5:$C$14,MATCH(B15,'Plan de Cuentas'!$B$5:$B$14,0)),"Cuenta no encontrada")) -> Gasto operativo
A16: 46065 | B16: Alquiler de local | C16: Alquiler de febrero | D16: 800 | E16: =IF(B16="","",IFERROR(INDEX('Plan de Cuentas'!$C$5:$C$14,MATCH(B16,'Plan de Cuentas'!$B$5:$B$14,0)),"Cuenta no encontrada")) -> Gasto operativo
... A24: 46108 | B24: Impuesto a la renta | C24: Pago a cuenta mensual | D24: 320 | E24: =IF(B24="","",IFERROR(INDEX('Plan de Cuentas'!$C$5:$C$14,MATCH(B24,'Plan de Cuentas'!$B$5:$B$14,0)),"Cuenta no encontrada")) -> Impuesto
E25: =IF(B25="","",IFERROR(INDEX('Plan de Cuentas'!$C$5:$C$14,MATCH(B25,'Plan de Cuentas'!$B$5:$B$14,0)),"Cuenta no encontrada"))
E26: =IF(B26="","",IFERROR(INDEX('Plan de Cuentas'!$C$5:$C$14,MATCH(B26,'Plan de Cuentas'!$B$5:$B$14,0)),"Cuenta no encontrada"))
E27: =IF(B27="","",IFERROR(INDEX('Plan de Cuentas'!$C$5:$C$14,MATCH(B27,'Plan de Cuentas'!$B$5:$B$14,0)),"Cuenta no encontrada"))
E28: =IF(B28="","",IFERROR(INDEX('Plan de Cuentas'!$C$5:$C$14,MATCH(B28,'Plan de Cuentas'!$B$5:$B$14,0)),"Cuenta no encontrada"))
E29: =IF(B29="","",IFERROR(INDEX('Plan de Cuentas'!$C$5:$C$14,MATCH(B29,'Plan de Cuentas'!$B$5:$B$14,0)),"Cuenta no encontrada"))
E30: =IF(B30="","",IFERROR(INDEX('Plan de Cuentas'!$C$5:$C$14,MATCH(B30,'Plan de Cuentas'!$B$5:$B$14,0)),"Cuenta no encontrada"))
E31: =IF(B31="","",IFERROR(INDEX('Plan de Cuentas'!$C$5:$C$14,MATCH(B31,'Plan de Cuentas'!$B$5:$B$14,0)),"Cuenta no encontrada"))
E32: =IF(B32="","",IFERROR(INDEX('Plan de Cuentas'!$C$5:$C$14,MATCH(B32,'Plan de Cuentas'!$B$5:$B$14,0)),"Cuenta no encontrada"))
E33: =IF(B33="","",IFERROR(INDEX('Plan de Cuentas'!$C$5:$C$14,MATCH(B33,'Plan de Cuentas'!$B$5:$B$14,0)),"Cuenta no encontrada"))
E34: =IF(B34="","",IFERROR(INDEX('Plan de Cuentas'!$C$5:$C$14,MATCH(B34,'Plan de Cuentas'!$B$5:$B$14,0)),"Cuenta no encontrada"))
E35: =IF(B35="","",IFERROR(INDEX('Plan de Cuentas'!$C$5:$C$14,MATCH(B35,'Plan de Cuentas'!$B$5:$B$14,0)),"Cuenta no encontrada"))
E36: =IF(B36="","",IFERROR(INDEX('Plan de Cuentas'!$C$5:$C$14,MATCH(B36,'Plan de Cuentas'!$B$5:$B$14,0)),"Cuenta no encontrada"))
... E204: =IF(B204="","",IFERROR(INDEX('Plan de Cuentas'!$C$5:$C$14,MATCH(B204,'Plan de Cuentas'!$B$5:$B$14,0)),"Cuenta no encontrada"))

Sheet Estado de Resultados
A2: ESTADO DE RESULTADOS
A3: =" Moneda: " & Configuracion!$C$8 & " | Año: " & Configuracion!$C$9 -> Moneda: Local | Año: 2026
A5: Concepto | B5: Ene | C5: Feb | D5: Mar | E5: Abr | F5: May | G5: Jun | H5: Jul | I5: Ago | J5: Sep | K5: Oct | L5: Nov | M5: Dic | N5: Total anual
A6: VENTAS | B6: =SUMIFS(Transacciones!$D$5:$D$204,Transacciones!$E$5:$E$204,"Ingreso",Transacciones!$A$5:$A$204,">="&DATE(Configuracion!$C$9,1,1),Transacciones!$A$5:$A$204,"<="&EOMONTH(DATE(Configuracion!$C$9,1,1),0))*Configuracion!$C$11 -> 4200 | C6: =SUMIFS(Transacciones!$D$5:$D$204,Transacciones!$E$5:$E$204,"Ingreso",Transacciones!$A$5:$A$204,">="&DATE(Configuracion!$C$9,2,1),Transacciones!$A$5:$A$204,"<="&EOMONTH(DATE(Configuracion!$C$9,2,1),0))*Configuracion!$C$11 -> 5100 | D6: =SUMIFS(Transacciones!$D$5:$D$204,Transacciones!$E$5:$E$204,"Ingreso",Transacciones!$A$5:$A$204,">="&DATE(Configuracion!$C$9,3,1),Transacciones!$A$5:$A$204,"<="&EOMONTH(DATE(Configuracion!$C$9,3,1),0))*Configuracion!$C$11 -> 4800 | E6: =SUMIFS(Transacciones!$D$5:$D$204,Transacciones!$E$5:$E$204,"Ingreso",Transacciones!$A$5:$A$204,">="&DATE(Configuracion!$C$9,4,1),Transacciones!$A$5:$A$204,"<="&EOMONTH(DATE(Configuracion!$C$9,4,1),0))*Configuracion!$C$11 -> 0 | F6: =SUMIFS(Transacciones!$D$5:$D$204,Transacciones!$E$5:$E$204,"Ingreso",Transacciones!$A$5:$A$204,">="&DATE(Configuracion!$C$9,5,1),Transacciones!$A$5:$A$204,"<="&EOMONTH(DATE(Configuracion!$C$9,5,1),0))*Configuracion!$C$11 -> 0 | G6: =SUMIFS(Transacciones!$D$5:$D$204,Transacciones!$E$5:$E$204,"Ingreso",Transacciones!$A$5:$A$204,">="&DATE(Configuracion!$C$9,6,1),Transacciones!$A$5:$A$204,"<="&EOMONTH(DATE(Configuracion!$C$9,6,1),0))*Configuracion!$C$11 -> 0 | H6: =SUMIFS(Transacciones!$D$5:$D$204,Transacciones!$E$5:$E$204,"Ingreso",Transacciones!$A$5:$A$204,">="&DATE(Configuracion!$C$9,7,1),Transacciones!$A$5:$A$204,"<="&EOMONTH(DATE(Configuracion!$C$9,7,1),0))*Configuracion!$C$11 -> 0 | I6: =SUMIFS(Transacciones!$D$5:$D$204,Transacciones!$E$5:$E$204,"Ingreso",Transacciones!$A$5:$A$204,">="&DATE(Configuracion!$C$9,8,1),Transacciones!$A$5:$A$204,"<="&EOMONTH(DATE(Configuracion!$C$9,8,1),0))*Configuracion!$C$11 -> 0 | J6: =SUMIFS(Transacciones!$D$5:$D$204,Transacciones!$E$5:$E$204,"Ingreso",Transacciones!$A$5:$A$204,">="&DATE(Configuracion!$C$9,9,1),Transacciones!$A$5:$A$204,"<="&EOMONTH(DATE(Configuracion!$C$9,9,1),0))*Configuracion!$C$11 -> 0 | K6: =SUMIFS(Transacciones!$D$5:$D$204,Transacciones!$E$5:$E$204,"Ingreso",Transacciones!$A$5:$A$204,">="&DATE(Configuracion!$C$9,10,1),Transacciones!$A$5:$A$204,"<="&EOMONTH(DATE(Configuracion!$C$9,10,1),0))*Configuracion!$C$11 -> 0 | L6: =SUMIFS(Transacciones!$D$5:$D$204,Transacciones!$E$5:$E$204,"Ingreso",Transacciones!$A$5:$A$204,">="&DATE(Configuracion!$C$9,11,1),Transacciones!$A$5:$A$204,"<="&EOMONTH(DATE(Configuracion!$C$9,11,1),0))*Configuracion!$C$11 -> 0 | M6: =SUMIFS(Transacciones!$D$5:$D$204,Transacciones!$E$5:$E$204,"Ingreso",Transacciones!$A$5:$A$204,">="&DATE(Configuracion!$C$9,12,1),Transacciones!$A$5:$A$204,"<="&EOMONTH(DATE(Configuracion!$C$9,12,1),0))*Configuracion!$C$11 -> 0 | N6: =SUM(B6:M6) -> 14100
A7: Costo de venta | B7: =SUMIFS(Transacciones!$D$5:$D$204,Transacciones!$E$5:$E$204,"Costo de venta",Transacciones!$A$5:$A$204,">="&DATE(Configuracion!$C$9,1,1),Transacciones!$A$5:$A$204,"<="&EOMONTH(DATE(Configuracion!$C$9,1,1),0))*Configuracion!$C$11 -> 1800 | C7: =SUMIFS(Transacciones!$D$5:$D$204,Transacciones!$E$5:$E$204,"Costo de venta",Transacciones!$A$5:$A$204,">="&DATE(Configuracion!$C$9,2,1),Transacciones!$A$5:$A$204,"<="&EOMONTH(DATE(Configuracion!$C$9,2,1),0))*Configuracion!$C$11 -> 1900 | D7: =SUMIFS(Transacciones!$D$5:$D$204,Transacciones!$E$5:$E$204,"Costo de venta",Transacciones!$A$5:$A$204,">="&DATE(Configuracion!$C$9,3,1),Transacciones!$A$5:$A$204,"<="&EOMONTH(DATE(Configuracion!$C$9,3,1),0))*Configuracion!$C$11 -> 2000 | E7: =SUMIFS(Transacciones!$D$5:$D$204,Transacciones!$E$5:$E$204,"Costo de venta",Transacciones!$A$5:$A$204,">="&DATE(Configuracion!$C$9,4,1),Transacciones!$A$5:$A$204,"<="&EOMONTH(DATE(Configuracion!$C$9,4,1),0))*Configuracion!$C$11 -> 0 | F7: =SUMIFS(Transacciones!$D$5:$D$204,Transacciones!$E$5:$E$204,"Costo de venta",Transacciones!$A$5:$A$204,">="&DATE(Configuracion!$C$9,5,1),Transacciones!$A$5:$A$204,"<="&EOMONTH(DATE(Configuracion!$C$9,5,1),0))*Configuracion!$C$11 -> 0 | G7: =SUMIFS(Transacciones!$D$5:$D$204,Transacciones!$E$5:$E$204,"Costo de venta",Transacciones!$A$5:$A$204,">="&DATE(Configuracion!$C$9,6,1),Transacciones!$A$5:$A$204,"<="&EOMONTH(DATE(Configuracion!$C$9,6,1),0))*Configuracion!$C$11 -> 0 | H7: =SUMIFS(Transacciones!$D$5:$D$204,Transacciones!$E$5:$E$204,"Costo de venta",Transacciones!$A$5:$A$204,">="&DATE(Configuracion!$C$9,7,1),Transacciones!$A$5:$A$204,"<="&EOMONTH(DATE(Configuracion!$C$9,7,1),0))*Configuracion!$C$11 -> 0 | I7: =SUMIFS(Transacciones!$D$5:$D$204,Transacciones!$E$5:$E$204,"Costo de venta",Transacciones!$A$5:$A$204,">="&DATE(Configuracion!$C$9,8,1),Transacciones!$A$5:$A$204,"<="&EOMONTH(DATE(Configuracion!$C$9,8,1),0))*Configuracion!$C$11 -> 0 | J7: =SUMIFS(Transacciones!$D$5:$D$204,Transacciones!$E$5:$E$204,"Costo de venta",Transacciones!$A$5:$A$204,">="&DATE(Configuracion!$C$9,9,1),Transacciones!$A$5:$A$204,"<="&EOMONTH(DATE(Configuracion!$C$9,9,1),0))*Configuracion!$C$11 -> 0 | K7: =SUMIFS(Transacciones!$D$5:$D$204,Transacciones!$E$5:$E$204,"Costo de venta",Transacciones!$A$5:$A$204,">="&DATE(Configuracion!$C$9,10,1),Transacciones!$A$5:$A$204,"<="&EOMONTH(DATE(Configuracion!$C$9,10,1),0))*Configuracion!$C$11 -> 0 | L7: =SUMIFS(Transacciones!$D$5:$D$204,Transacciones!$E$5:$E$204,"Costo de venta",Transacciones!$A$5:$A$204,">="&DATE(Configuracion!$C$9,11,1),Transacciones!$A$5:$A$204,"<="&EOMONTH(DATE(Configuracion!$C$9,11,1),0))*Configuracion!$C$11 -> 0 | M7: =SUMIFS(Transacciones!$D$5:$D$204,Transacciones!$E$5:$E$204,"Costo de venta",Transacciones!$A$5:$A$204,">="&DATE(Configuracion!$C$9,12,1),Transacciones!$A$5:$A$204,"<="&EOMONTH(DATE(Configuracion!$C$9,12,1),0))*Configuracion!$C$11 -> 0 | N7: =SUM(B7:M7) -> 5700
A8: UTILIDAD BRUTA | B8: =B6-B7 -> 2400 | C8: =C6-C7 -> 3200 | D8: =D6-D7 -> 2800 | E8: =E6-E7 -> 0 | F8: =F6-F7 -> 0 | G8: =G6-G7 -> 0 | H8: =H6-H7 -> 0 | I8: =I6-I7 -> 0 | ... N8: =N6-N7 -> 8400
A9: Gastos operativos | B9: =SUMIFS(Transacciones!$D$5:$D$204,Transacciones!$E$5:$E$204,"Gasto operativo",Transacciones!$A$5:$A$204,">="&DATE(Configuracion!$C$9,1,1),Transacciones!$A$5:$A$204,"<="&EOMONTH(DATE(Configuracion!$C$9,1,1),0))*Configuracion!$C$11 -> 2180 | C9: =SUMIFS(Transacciones!$D$5:$D$204,Transacciones!$E$5:$E$204,"Gasto operativo",Transacciones!$A$5:$A$204,">="&DATE(Configuracion!$C$9,2,1),Transacciones!$A$5:$A$204,"<="&EOMONTH(DATE(Configuracion!$C$9,2,1),0))*Configuracion!$C$11 -> 2000 | D9: =SUMIFS(Transacciones!$D$5:$D$204,Transacciones!$E$5:$E$204,"Gasto operativo",Transacciones!$A$5:$A$204,">="&DATE(Configuracion!$C$9,3,1),Transacciones!$A$5:$A$204,"<="&EOMONTH(DATE(Configuracion!$C$9,3,1),0))*Configuracion!$C$11 -> 2000 | E9: =SUMIFS(Transacciones!$D$5:$D$204,Transacciones!$E$5:$E$204,"Gasto operativo",Transacciones!$A$5:$A$204,">="&DATE(Configuracion!$C$9,4,1),Transacciones!$A$5:$A$204,"<="&EOMONTH(DATE(Configuracion!$C$9,4,1),0))*Configuracion!$C$11 -> 0 | F9: =SUMIFS(Transacciones!$D$5:$D$204,Transacciones!$E$5:$E$204,"Gasto operativo",Transacciones!$A$5:$A$204,">="&DATE(Configuracion!$C$9,5,1),Transacciones!$A$5:$A$204,"<="&EOMONTH(DATE(Configuracion!$C$9,5,1),0))*Configuracion!$C$11 -> 0 | G9: =SUMIFS(Transacciones!$D$5:$D$204,Transacciones!$E$5:$E$204,"Gasto operativo",Transacciones!$A$5:$A$204,">="&DATE(Configuracion!$C$9,6,1),Transacciones!$A$5:$A$204,"<="&EOMONTH(DATE(Configuracion!$C$9,6,1),0))*Configuracion!$C$11 -> 0 | H9: =SUMIFS(Transacciones!$D$5:$D$204,Transacciones!$E$5:$E$204,"Gasto operativo",Transacciones!$A$5:$A$204,">="&DATE(Configuracion!$C$9,7,1),Transacciones!$A$5:$A$204,"<="&EOMONTH(DATE(Configuracion!$C$9,7,1),0))*Configuracion!$C$11 -> 0 | I9: =SUMIFS(Transacciones!$D$5:$D$204,Transacciones!$E$5:$E$204,"Gasto operativo",Transacciones!$A$5:$A$204,">="&DATE(Configuracion!$C$9,8,1),Transacciones!$A$5:$A$204,"<="&EOMONTH(DATE(Configuracion!$C$9,8,1),0))*Configuracion!$C$11 -> 0 | J9: =SUMIFS(Transacciones!$D$5:$D$204,Transacciones!$E$5:$E$204,"Gasto operativo",Transacciones!$A$5:$A$204,">="&DATE(Configuracion!$C$9,9,1),Transacciones!$A$5:$A$204,"<="&EOMONTH(DATE(Configuracion!$C$9,9,1),0))*Configuracion!$C$11 -> 0 | K9: =SUMIFS(Transacciones!$D$5:$D$204,Transacciones!$E$5:$E$204,"Gasto operativo",Transacciones!$A$5:$A$204,">="&DATE(Configuracion!$C$9,10,1),Transacciones!$A$5:$A$204,"<="&EOMONTH(DATE(Configuracion!$C$9,10,1),0))*Configuracion!$C$11 -> 0 | L9: =SUMIFS(Transacciones!$D$5:$D$204,Transacciones!$E$5:$E$204,"Gasto operativo",Transacciones!$A$5:$A$204,">="&DATE(Configuracion!$C$9,11,1),Transacciones!$A$5:$A$204,"<="&EOMONTH(DATE(Configuracion!$C$9,11,1),0))*Configuracion!$C$11 -> 0 | M9: =SUMIFS(Transacciones!$D$5:$D$204,Transacciones!$E$5:$E$204,"Gasto operativo",Transacciones!$A$5:$A$204,">="&DATE(Configuracion!$C$9,12,1),Transacciones!$A$5:$A$204,"<="&EOMONTH(DATE(Configuracion!$C$9,12,1),0))*Configuracion!$C$11 -> 0 | N9: =SUM(B9:M9) -> 6180
A10: Gastos administrativos | B10: =SUMIFS(Transacciones!$D$5:$D$204,Transacciones!$E$5:$E$204,"Gasto administrativo",Transacciones!$A$5:$A$204,">="&DATE(Configuracion!$C$9,1,1),Transacciones!$A$5:$A$204,"<="&EOMONTH(DATE(Configuracion!$C$9,1,1),0))*Configuracion!$C$11 -> 250 | C10: =SUMIFS(Transacciones!$D$5:$D$204,Transacciones!$E$5:$E$204,"Gasto administrativo",Transacciones!$A$5:$A$204,">="&DATE(Configuracion!$C$9,2,1),Transacciones!$A$5:$A$204,"<="&EOMONTH(DATE(Configuracion!$C$9,2,1),0))*Configuracion!$C$11 -> 60 | D10: =SUMIFS(Transacciones!$D$5:$D$204,Transacciones!$E$5:$E$204,"Gasto administrativo",Transacciones!$A$5:$A$204,">="&DATE(Configuracion!$C$9,3,1),Transacciones!$A$5:$A$204,"<="&EOMONTH(DATE(Configuracion!$C$9,3,1),0))*Configuracion!$C$11 -> 300 | E10: =SUMIFS(Transacciones!$D$5:$D$204,Transacciones!$E$5:$E$204,"Gasto administrativo",Transacciones!$A$5:$A$204,">="&DATE(Configuracion!$C$9,4,1),Transacciones!$A$5:$A$204,"<="&EOMONTH(DATE(Configuracion!$C$9,4,1),0))*Configuracion!$C$11 -> 0 | F10: =SUMIFS(Transacciones!$D$5:$D$204,Transacciones!$E$5:$E$204,"Gasto administrativo",Transacciones!$A$5:$A$204,">="&DATE(Configuracion!$C$9,5,1),Transacciones!$A$5:$A$204,"<="&EOMONTH(DATE(Configuracion!$C$9,5,1),0))*Configuracion!$C$11 -> 0 | G10: =SUMIFS(Transacciones!$D$5:$D$204,Transacciones!$E$5:$E$204,"Gasto administrativo",Transacciones!$A$5:$A$204,">="&DATE(Configuracion!$C$9,6,1),Transacciones!$A$5:$A$204,"<="&EOMONTH(DATE(Configuracion!$C$9,6,1),0))*Configuracion!$C$11 -> 0 | H10: =SUMIFS(Transacciones!$D$5:$D$204,Transacciones!$E$5:$E$204,"Gasto administrativo",Transacciones!$A$5:$A$204,">="&DATE(Configuracion!$C$9,7,1),Transacciones!$A$5:$A$204,"<="&EOMONTH(DATE(Configuracion!$C$9,7,1),0))*Configuracion!$C$11 -> 0 | I10: =SUMIFS(Transacciones!$D$5:$D$204,Transacciones!$E$5:$E$204,"Gasto administrativo",Transacciones!$A$5:$A$204,">="&DATE(Configuracion!$C$9,8,1),Transacciones!$A$5:$A$204,"<="&EOMONTH(DATE(Configuracion!$C$9,8,1),0))*Configuracion!$C$11 -> 0 | J10: =SUMIFS(Transacciones!$D$5:$D$204,Transacciones!$E$5:$E$204,"Gasto administrativo",Transacciones!$A$5:$A$204,">="&DATE(Configuracion!$C$9,9,1),Transacciones!$A$5:$A$204,"<="&EOMONTH(DATE(Configuracion!$C$9,9,1),0))*Configuracion!$C$11 -> 0 | K10: =SUMIFS(Transacciones!$D$5:$D$204,Transacciones!$E$5:$E$204,"Gasto administrativo",Transacciones!$A$5:$A$204,">="&DATE(Configuracion!$C$9,10,1),Transacciones!$A$5:$A$204,"<="&EOMONTH(DATE(Configuracion!$C$9,10,1),0))*Configuracion!$C$11 -> 0 | L10: =SUMIFS(Transacciones!$D$5:$D$204,Transacciones!$E$5:$E$204,"Gasto administrativo",Transacciones!$A$5:$A$204,">="&DATE(Configuracion!$C$9,11,1),Transacciones!$A$5:$A$204,"<="&EOMONTH(DATE(Configuracion!$C$9,11,1),0))*Configuracion!$C$11 -> 0 | M10: =SUMIFS(Transacciones!$D$5:$D$204,Transacciones!$E$5:$E$204,"Gasto administrativo",Transacciones!$A$5:$A$204,">="&DATE(Configuracion!$C$9,12,1),Transacciones!$A$5:$A$204,"<="&EOMONTH(DATE(Configuracion!$C$9,12,1),0))*Configuracion!$C$11 -> 0 | N10: =SUM(B10:M10) -> 610
A11: UTILIDAD OPERATIVA | B11: =B8-B9-B10 -> -30 | C11: =C8-C9-C10 -> 1140 | D11: =D8-D9-D10 -> 500 | E11: =E8-E9-E10 -> 0 | F11: =F8-F9-F10 -> 0 | G11: =G8-G9-G10 -> 0 | H11: =H8-H9-H10 -> 0 | I11: =I8-I9-I10 -> 0 | ... N11: =N8-N9-N10 -> 1610
A12: Gastos financieros | B12: =SUMIFS(Transacciones!$D$5:$D$204,Transacciones!$E$5:$E$204,"Gasto financiero",Transacciones!$A$5:$A$204,">="&DATE(Configuracion!$C$9,1,1),Transacciones!$A$5:$A$204,"<="&EOMONTH(DATE(Configuracion!$C$9,1,1),0))*Configuracion!$C$11 -> 40 | C12: =SUMIFS(Transacciones!$D$5:$D$204,Transacciones!$E$5:$E$204,"Gasto financiero",Transacciones!$A$5:$A$204,">="&DATE(Configuracion!$C$9,2,1),Transacciones!$A$5:$A$204,"<="&EOMONTH(DATE(Configuracion!$C$9,2,1),0))*Configuracion!$C$11 -> 0 | D12: =SUMIFS(Transacciones!$D$5:$D$204,Transacciones!$E$5:$E$204,"Gasto financiero",Transacciones!$A$5:$A$204,">="&DATE(Configuracion!$C$9,3,1),Transacciones!$A$5:$A$204,"<="&EOMONTH(DATE(Configuracion!$C$9,3,1),0))*Configuracion!$C$11 -> 0 | E12: =SUMIFS(Transacciones!$D$5:$D$204,Transacciones!$E$5:$E$204,"Gasto financiero",Transacciones!$A$5:$A$204,">="&DATE(Configuracion!$C$9,4,1),Transacciones!$A$5:$A$204,"<="&EOMONTH(DATE(Configuracion!$C$9,4,1),0))*Configuracion!$C$11 -> 0 | F12: =SUMIFS(Transacciones!$D$5:$D$204,Transacciones!$E$5:$E$204,"Gasto financiero",Transacciones!$A$5:$A$204,">="&DATE(Configuracion!$C$9,5,1),Transacciones!$A$5:$A$204,"<="&EOMONTH(DATE(Configuracion!$C$9,5,1),0))*Configuracion!$C$11 -> 0 | G12: =SUMIFS(Transacciones!$D$5:$D$204,Transacciones!$E$5:$E$204,"Gasto financiero",Transacciones!$A$5:$A$204,">="&DATE(Configuracion!$C$9,6,1),Transacciones!$A$5:$A$204,"<="&EOMONTH(DATE(Configuracion!$C$9,6,1),0))*Configuracion!$C$11 -> 0 | H12: =SUMIFS(Transacciones!$D$5:$D$204,Transacciones!$E$5:$E$204,"Gasto financiero",Transacciones!$A$5:$A$204,">="&DATE(Configuracion!$C$9,7,1),Transacciones!$A$5:$A$204,"<="&EOMONTH(DATE(Configuracion!$C$9,7,1),0))*Configuracion!$C$11 -> 0 | I12: =SUMIFS(Transacciones!$D$5:$D$204,Transacciones!$E$5:$E$204,"Gasto financiero",Transacciones!$A$5:$A$204,">="&DATE(Configuracion!$C$9,8,1),Transacciones!$A$5:$A$204,"<="&EOMONTH(DATE(Configuracion!$C$9,8,1),0))*Configuracion!$C$11 -> 0 | J12: =SUMIFS(Transacciones!$D$5:$D$204,Transacciones!$E$5:$E$204,"Gasto financiero",Transacciones!$A$5:$A$204,">="&DATE(Configuracion!$C$9,9,1),Transacciones!$A$5:$A$204,"<="&EOMONTH(DATE(Configuracion!$C$9,9,1),0))*Configuracion!$C$11 -> 0 | K12: =SUMIFS(Transacciones!$D$5:$D$204,Transacciones!$E$5:$E$204,"Gasto financiero",Transacciones!$A$5:$A$204,">="&DATE(Configuracion!$C$9,10,1),Transacciones!$A$5:$A$204,"<="&EOMONTH(DATE(Configuracion!$C$9,10,1),0))*Configuracion!$C$11 -> 0 | L12: =SUMIFS(Transacciones!$D$5:$D$204,Transacciones!$E$5:$E$204,"Gasto financiero",Transacciones!$A$5:$A$204,">="&DATE(Configuracion!$C$9,11,1),Transacciones!$A$5:$A$204,"<="&EOMONTH(DATE(Configuracion!$C$9,11,1),0))*Configuracion!$C$11 -> 0 | M12: =SUMIFS(Transacciones!$D$5:$D$204,Transacciones!$E$5:$E$204,"Gasto financiero",Transacciones!$A$5:$A$204,">="&DATE(Configuracion!$C$9,12,1),Transacciones!$A$5:$A$204,"<="&EOMONTH(DATE(Configuracion!$C$9,12,1),0))*Configuracion!$C$11 -> 0 | N12: =SUM(B12:M12) -> 40
A13: Impuestos | B13: =SUMIFS(Transacciones!$D$5:$D$204,Transacciones!$E$5:$E$204,"Impuesto",Transacciones!$A$5:$A$204,">="&DATE(Configuracion!$C$9,1,1),Transacciones!$A$5:$A$204,"<="&EOMONTH(DATE(Configuracion!$C$9,1,1),0))*Configuracion!$C$11 -> 0 | C13: =SUMIFS(Transacciones!$D$5:$D$204,Transacciones!$E$5:$E$204,"Impuesto",Transacciones!$A$5:$A$204,">="&DATE(Configuracion!$C$9,2,1),Transacciones!$A$5:$A$204,"<="&EOMONTH(DATE(Configuracion!$C$9,2,1),0))*Configuracion!$C$11 -> 300 | D13: =SUMIFS(Transacciones!$D$5:$D$204,Transacciones!$E$5:$E$204,"Impuesto",Transacciones!$A$5:$A$204,">="&DATE(Configuracion!$C$9,3,1),Transacciones!$A$5:$A$204,"<="&EOMONTH(DATE(Configuracion!$C$9,3,1),0))*Configuracion!$C$11 -> 320 | E13: =SUMIFS(Transacciones!$D$5:$D$204,Transacciones!$E$5:$E$204,"Impuesto",Transacciones!$A$5:$A$204,">="&DATE(Configuracion!$C$9,4,1),Transacciones!$A$5:$A$204,"<="&EOMONTH(DATE(Configuracion!$C$9,4,1),0))*Configuracion!$C$11 -> 0 | F13: =SUMIFS(Transacciones!$D$5:$D$204,Transacciones!$E$5:$E$204,"Impuesto",Transacciones!$A$5:$A$204,">="&DATE(Configuracion!$C$9,5,1),Transacciones!$A$5:$A$204,"<="&EOMONTH(DATE(Configuracion!$C$9,5,1),0))*Configuracion!$C$11 -> 0 | G13: =SUMIFS(Transacciones!$D$5:$D$204,Transacciones!$E$5:$E$204,"Impuesto",Transacciones!$A$5:$A$204,">="&DATE(Configuracion!$C$9,6,1),Transacciones!$A$5:$A$204,"<="&EOMONTH(DATE(Configuracion!$C$9,6,1),0))*Configuracion!$C$11 -> 0 | H13: =SUMIFS(Transacciones!$D$5:$D$204,Transacciones!$E$5:$E$204,"Impuesto",Transacciones!$A$5:$A$204,">="&DATE(Configuracion!$C$9,7,1),Transacciones!$A$5:$A$204,"<="&EOMONTH(DATE(Configuracion!$C$9,7,1),0))*Configuracion!$C$11 -> 0 | I13: =SUMIFS(Transacciones!$D$5:$D$204,Transacciones!$E$5:$E$204,"Impuesto",Transacciones!$A$5:$A$204,">="&DATE(Configuracion!$C$9,8,1),Transacciones!$A$5:$A$204,"<="&EOMONTH(DATE(Configuracion!$C$9,8,1),0))*Configuracion!$C$11 -> 0 | J13: =SUMIFS(Transacciones!$D$5:$D$204,Transacciones!$E$5:$E$204,"Impuesto",Transacciones!$A$5:$A$204,">="&DATE(Configuracion!$C$9,9,1),Transacciones!$A$5:$A$204,"<="&EOMONTH(DATE(Configuracion!$C$9,9,1),0))*Configuracion!$C$11 -> 0 | K13: =SUMIFS(Transacciones!$D$5:$D$204,Transacciones!$E$5:$E$204,"Impuesto",Transacciones!$A$5:$A$204,">="&DATE(Configuracion!$C$9,10,1),Transacciones!$A$5:$A$204,"<="&EOMONTH(DATE(Configuracion!$C$9,10,1),0))*Configuracion!$C$11 -> 0 | L13: =SUMIFS(Transacciones!$D$5:$D$204,Transacciones!$E$5:$E$204,"Impuesto",Transacciones!$A$5:$A$204,">="&DATE(Configuracion!$C$9,11,1),Transacciones!$A$5:$A$204,"<="&EOMONTH(DATE(Configuracion!$C$9,11,1),0))*Configuracion!$C$11 -> 0 | M13: =SUMIFS(Transacciones!$D$5:$D$204,Transacciones!$E$5:$E$204,"Impuesto",Transacciones!$A$5:$A$204,">="&DATE(Configuracion!$C$9,12,1),Transacciones!$A$5:$A$204,"<="&EOMONTH(DATE(Configuracion!$C$9,12,1),0))*Configuracion!$C$11 -> 0 | N13: =SUM(B13:M13) -> 620
A14: UTILIDAD NETA | B14: =B11-B12-B13 -> -70 | C14: =C11-C12-C13 -> 840 | D14: =D11-D12-D13 -> 180 | E14: =E11-E12-E13 -> 0 | F14: =F11-F12-F13 -> 0 | G14: =G11-G12-G13 -> 0 | H14: =H11-H12-H13 -> 0 | I14: =I11-I12-I13 -> 0 | ... N14: =N11-N12-N13 -> 950
A16: Margen bruto (%) | B16: =IF(B6=0,0,B8/B6) -> 0.57142857 | C16: =IF(C6=0,0,C8/C6) -> 0.62745098 | D16: =IF(D6=0,0,D8/D6) -> 0.58333333 | E16: =IF(E6=0,0,E8/E6) -> 0 | F16: =IF(F6=0,0,F8/F6) -> 0 | G16: =IF(G6=0,0,G8/G6) -> 0 | H16: =IF(H6=0,0,H8/H6) -> 0 | I16: =IF(I6=0,0,I8/I6) -> 0 | ... N16: =IF(N6=0,0,N8/N6) -> 0.59574468
A17: Margen neto (%) | B17: =IF(B6=0,0,B14/B6) -> -0.016666667 | C17: =IF(C6=0,0,C14/C6) -> 0.16470588 | D17: =IF(D6=0,0,D14/D6) -> 0.0375 | E17: =IF(E6=0,0,E14/E6) -> 0 | F17: =IF(F6=0,0,F14/F6) -> 0 | G17: =IF(G6=0,0,G14/G6) -> 0 | H17: =IF(H6=0,0,H14/H6) -> 0 | I17: =IF(I6=0,0,I14/I6) -> 0 | ... N17: =IF(N6=0,0,N14/N6) -> 0.067375887

Sheet Dashboard
B2: DASHBOARD · CONTABILIDAD BÁSICA
B3: =" Moneda: " & Configuracion!$C$8 & " | Año: " & Configuracion!$C$9 -> Moneda: Local | Año: 2026
K4: Tipo | L4: Monto
B5: VENTAS DEL AÑO | D5: UTILIDAD BRUTA | F5: UTILIDAD NETA | H5: MARGEN NETO | K5: Costo de venta | L5: ='Estado de Resultados'!N7 -> 5700
B6: =Configuracion!$C$12&" "&TEXT('Estado de Resultados'!N6,"#,##0.00") -> S/ 14,100.00 | D6: =Configuracion!$C$12&" "&TEXT('Estado de Resultados'!N8,"#,##0.00") -> S/ 8,400.00 | F6: =Configuracion!$C$12&" "&TEXT('Estado de Resultados'!N14,"#,##0.00") -> S/ 950.00 | H6: =IF('Estado de Resultados'!N6=0,"0.0%",TEXT('Estado de Resultados'!N14/'Estado de Resultados'!N6,"0.0%")) -> 6.7% | K6: Gastos operativos | L6: ='Estado de Resultados'!N9 -> 6180
K7: Gastos administrativos | L7: ='Estado de Resultados'!N10 -> 610
K8: Gastos financieros | L8: ='Estado de Resultados'!N12 -> 40
K9: Impuestos | L9: ='Estado de Resultados'!N13 -> 620
