Workbook

Sheet Portada
B2: LÍNEA DE PRODUCTOS DIGITALES · PLANTILLAS EXCEL
B4: NÓMINA BÁSICA
B7: Organiza la planilla de tu equipo: sueldos, bonificaciones y descuentos, mes a mes, y obtén el sueldo neto de cada colaborador sin fórmulas complicadas — con panel de control, gráficos automáticos y selector de moneda (local / USD).
B10: QUÉ INCLUYE ESTA PLANTILLA
B11: ✔ Dashboard con indicadores clave (KPIs) y gráficos automáticos
B12: ✔ Fórmulas automáticas: nada que calcular a mano
B13: ✔ Cálculo automático de descuentos (seguro social e impuesto) y sueldo neto
B14: ✔ Gráficos: pastel (composición de planilla), barras y evolución mensual
B15: ✔ Resumen dinámico tipo tabla dinámica por colaborador y por mes
B16: ✔ Listas desplegables y validación de datos en cada registro
B17: ✔ Selector de moneda: local o USD, con tipo de cambio editable
B18: ✔ Hoja de instrucciones paso a paso
... B24: © Tu Marca de Plantillas · www.tumarca.com

Sheet Instrucciones
B2: CÓMO USAR ESTA PLANTILLA
B4: 1. Configuración
B5: Define el símbolo de tu moneda local, el tipo de cambio, las tasas de descuento (seguro social e impuesto/retención), el mes que quieres analizar y si la plantilla se muestra en moneda LOCAL o USD.
B7: 2. Empleados
B8: En 'Empleados' registra a cada colaborador: nombre, cargo, fecha de ingreso y sueldo base mensual. Hay espacio para hasta 10 colaboradores.
B10: 3. Bonificaciones
B11: En 'Bonificaciones' registra, mes a mes, cualquier bono, comisión u horas extra de cada colaborador (además de su sueldo base).
B13: 4. Resumen automático
B14: La hoja 'Resumen' calcula, para el mes elegido, el total de ingresos, los descuentos y el sueldo neto de cada colaborador, y totaliza la planilla mes a mes durante el año.
B16: 5. Dashboard
B17: La hoja 'Dashboard' muestra tu planilla bruta y neta del mes, el número de colaboradores y los descuentos totales, con gráficos que se actualizan solos.
B19: 6. Cambiar de mes o de moneda
... B28: Soporte y otras plantillas de esta línea de productos: www.tumarca.com

Sheet Configuracion
B2: CONFIGURACIÓN Y MONEDA
B4: Parámetro | C4: Valor | D4: Notas
B5: Nombre de moneda local | C5: Soles (PEN) | D5: Solo referencia. Escribe el nombre de tu moneda.
B6: Símbolo de moneda local | C6: S/ | D6: Símbolo que se usará en el Dashboard cuando la vista esté en LOCAL.
B7: Tipo de cambio (1 USD =) | C7: 3.75 | D7: Cuántas unidades de tu moneda local equivalen a 1 USD.
B8: Moneda de visualización | C8: Local | D8: Elige LOCAL o USD. Afecta Resumen y Dashboard.
B9: Tasa de seguro social (%) | C9: 0.13 | D9: Porcentaje de descuento por seguro social/pensión sobre el total de ingresos.
B10: Tasa de impuesto/retención (%) | C10: 0.08 | D10: Porcentaje de retención de impuesto sobre el total de ingresos.
B11: Mes seleccionado | C11: Enero | D11: Mes que se muestra en Resumen y Dashboard.
B12: Año de análisis | C12: 2026 | D12: Año que se usa como referencia.
B13: Valores calculados (no editar)
B14: Número de mes seleccionado | C14: =MATCH(C11,{"Enero","Febrero","Marzo","Abril","Mayo","Junio","Julio","Agosto","Septiembre","Octubre","Noviembre","Diciembre"},0) -> 1 | D14: 1=Enero ... 12=Diciembre.
B15: Símbolo de moneda actual | C15: =IF(C8="USD","US$",C6) -> S/ | D15: Símbolo que verás en el Dashboard según la moneda elegida.
B17: Cambia 'Moneda de visualización' entre Local y USD para recalcular automáticamente toda la plantilla.

Sheet Empleados
A2: PLANTILLA DE EMPLEADOS
A4: Código | B4: Nombre | C4: Cargo | D4: Fecha de ingreso | E4: Sueldo base mensual
A5: EMP-01 | B5: Ana Torres | C5: Gerente General | D5: 44986 | E5: 2500
A6: EMP-02 | B6: Luis Medina | C6: Contador | D6: 45092 | E6: 1600
A7: EMP-03 | B7: Sofía Vargas | C7: Ejecutiva de Ventas | D7: 45301 | E7: 1200
A8: EMP-04 | B8: Jorge Paredes | C8: Asistente Administrativo | D8: 45383 | E8: 1000
A9: EMP-05 | B9: Valeria Ríos | C9: Diseñadora | D9: 45689 | E9: 1300

Sheet Bonificaciones
A2: BONIFICACIONES / HORAS EXTRA (por colaborador y mes)
A3: Monto adicional al sueldo base de cada colaborador en cada mes (bonos, comisiones, horas extra).
A4: Colaborador | B4: Ene | C4: Feb | D4: Mar | E4: Abr | F4: May | G4: Jun | H4: Jul | I4: Ago | J4: Sep | K4: Oct | L4: Nov | M4: Dic | N4: Total anual
A5: =Empleados!$B$5 -> Ana Torres | B5: 200 | C5: 0 | D5: 300 | E5: 0 | F5: 0 | G5: 200 | H5: 0 | I5: 0 | J5: 300 | K5: 0 | L5: 0 | M5: 500 | N5: =SUM(B5:M5) -> 1500
A6: =Empleados!$B$6 -> Luis Medina | B6: 0 | C6: 0 | D6: 100 | E6: 0 | F6: 0 | G6: 0 | H6: 0 | I6: 0 | J6: 100 | K6: 0 | L6: 0 | M6: 200 | N6: =SUM(B6:M6) -> 400
A7: =Empleados!$B$7 -> Sofía Vargas | B7: 150 | C7: 220 | D7: 180 | E7: 0 | F7: 0 | G7: 0 | H7: 0 | I7: 0 | J7: 0 | K7: 0 | L7: 0 | M7: 300 | N7: =SUM(B7:M7) -> 850
A8: =Empleados!$B$8 -> Jorge Paredes | B8: 0 | C8: 0 | D8: 0 | E8: 0 | F8: 0 | G8: 0 | H8: 0 | I8: 0 | J8: 0 | K8: 0 | L8: 0 | M8: 150 | N8: =SUM(B8:M8) -> 150
A9: =Empleados!$B$9 -> Valeria Ríos | B9: 0 | C9: 100 | D9: 0 | E9: 0 | F9: 0 | G9: 0 | H9: 0 | I9: 0 | J9: 0 | K9: 0 | L9: 0 | M9: 200 | N9: =SUM(B9:M9) -> 300
A10: =Empleados!$B$10 -> 0 | N10: =SUM(B10:M10) -> 0
A11: =Empleados!$B$11 -> 0 | N11: =SUM(B11:M11) -> 0
A12: =Empleados!$B$12 -> 0 | N12: =SUM(B12:M12) -> 0
A13: =Empleados!$B$13 -> 0 | N13: =SUM(B13:M13) -> 0
A14: =Empleados!$B$14 -> 0 | N14: =SUM(B14:M14) -> 0

Sheet Resumen
B2: RESUMEN DINÁMICO (se actualiza solo)
B3: =" Mes: " & Configuracion!$C$11 & " | Moneda: " & Configuracion!$C$8 -> Mes: Enero | Moneda: Local
B5: PLANILLA POR COLABORADOR (mes seleccionado)
B6: Colaborador | C6: Cargo | D6: Sueldo base | E6: Bonificación | F6: Total ingresos | G6: Descuentos | H6: Sueldo neto
B7: =IF(Empleados!$A$5="","",Empleados!$B$5) -> Ana Torres | C7: =IF(Empleados!$A$5="","",Empleados!$C$5) -> Gerente General | D7: =IF(Empleados!$A$5="",0,Empleados!$E$5*Configuracion!$C$14) -> 2500 | E7: =IF(Empleados!$A$5="",0,INDEX(Bonificaciones!$B$5:$M$5,Configuracion!$C$14)*Configuracion!$C$14) -> 200 | F7: =D7+E7 -> 2700 | G7: =F7*(Configuracion!$C$9+Configuracion!$C$10) -> 567 | H7: =F7-G7 -> 2133
B8: =IF(Empleados!$A$6="","",Empleados!$B$6) -> Luis Medina | C8: =IF(Empleados!$A$6="","",Empleados!$C$6) -> Contador | D8: =IF(Empleados!$A$6="",0,Empleados!$E$6*Configuracion!$C$14) -> 1600 | E8: =IF(Empleados!$A$6="",0,INDEX(Bonificaciones!$B$6:$M$6,Configuracion!$C$14)*Configuracion!$C$14) -> 0 | F8: =D8+E8 -> 1600 | G8: =F8*(Configuracion!$C$9+Configuracion!$C$10) -> 336 | H8: =F8-G8 -> 1264
B9: =IF(Empleados!$A$7="","",Empleados!$B$7) -> Sofía Vargas | C9: =IF(Empleados!$A$7="","",Empleados!$C$7) -> Ejecutiva de Ventas | D9: =IF(Empleados!$A$7="",0,Empleados!$E$7*Configuracion!$C$14) -> 1200 | E9: =IF(Empleados!$A$7="",0,INDEX(Bonificaciones!$B$7:$M$7,Configuracion!$C$14)*Configuracion!$C$14) -> 150 | F9: =D9+E9 -> 1350 | G9: =F9*(Configuracion!$C$9+Configuracion!$C$10) -> 283.5 | H9: =F9-G9 -> 1066.5
B10: =IF(Empleados!$A$8="","",Empleados!$B$8) -> Jorge Paredes | C10: =IF(Empleados!$A$8="","",Empleados!$C$8) -> Asistente Administrativo | D10: =IF(Empleados!$A$8="",0,Empleados!$E$8*Configuracion!$C$14) -> 1000 | E10: =IF(Empleados!$A$8="",0,INDEX(Bonificaciones!$B$8:$M$8,Configuracion!$C$14)*Configuracion!$C$14) -> 0 | F10: =D10+E10 -> 1000 | G10: =F10*(Configuracion!$C$9+Configuracion!$C$10) -> 210 | H10: =F10-G10 -> 790
B11: =IF(Empleados!$A$9="","",Empleados!$B$9) -> Valeria Ríos | C11: =IF(Empleados!$A$9="","",Empleados!$C$9) -> Diseñadora | D11: =IF(Empleados!$A$9="",0,Empleados!$E$9*Configuracion!$C$14) -> 1300 | E11: =IF(Empleados!$A$9="",0,INDEX(Bonificaciones!$B$9:$M$9,Configuracion!$C$14)*Configuracion!$C$14) -> 0 | F11: =D11+E11 -> 1300 | G11: =F11*(Configuracion!$C$9+Configuracion!$C$10) -> 273 | H11: =F11-G11 -> 1027
B12: =IF(Empleados!$A$10="","",Empleados!$B$10) | C12: =IF(Empleados!$A$10="","",Empleados!$C$10) | D12: =IF(Empleados!$A$10="",0,Empleados!$E$10*Configuracion!$C$14) -> 0 | E12: =IF(Empleados!$A$10="",0,INDEX(Bonificaciones!$B$10:$M$10,Configuracion!$C$14)*Configuracion!$C$14) -> 0 | F12: =D12+E12 -> 0 | G12: =F12*(Configuracion!$C$9+Configuracion!$C$10) -> 0 | H12: =F12-G12 -> 0
B13: =IF(Empleados!$A$11="","",Empleados!$B$11) | C13: =IF(Empleados!$A$11="","",Empleados!$C$11) | D13: =IF(Empleados!$A$11="",0,Empleados!$E$11*Configuracion!$C$14) -> 0 | E13: =IF(Empleados!$A$11="",0,INDEX(Bonificaciones!$B$11:$M$11,Configuracion!$C$14)*Configuracion!$C$14) -> 0 | F13: =D13+E13 -> 0 | G13: =F13*(Configuracion!$C$9+Configuracion!$C$10) -> 0 | H13: =F13-G13 -> 0
B14: =IF(Empleados!$A$12="","",Empleados!$B$12) | C14: =IF(Empleados!$A$12="","",Empleados!$C$12) | D14: =IF(Empleados!$A$12="",0,Empleados!$E$12*Configuracion!$C$14) -> 0 | E14: =IF(Empleados!$A$12="",0,INDEX(Bonificaciones!$B$12:$M$12,Configuracion!$C$14)*Configuracion!$C$14) -> 0 | F14: =D14+E14 -> 0 | G14: =F14*(Configuracion!$C$9+Configuracion!$C$10) -> 0 | H14: =F14-G14 -> 0
B15: =IF(Empleados!$A$13="","",Empleados!$B$13) | C15: =IF(Empleados!$A$13="","",Empleados!$C$13) | D15: =IF(Empleados!$A$13="",0,Empleados!$E$13*Configuracion!$C$14) -> 0 | E15: =IF(Empleados!$A$13="",0,INDEX(Bonificaciones!$B$13:$M$13,Configuracion!$C$14)*Configuracion!$C$14) -> 0 | F15: =D15+E15 -> 0 | G15: =F15*(Configuracion!$C$9+Configuracion!$C$10) -> 0 | H15: =F15-G15 -> 0
B16: =IF(Empleados!$A$14="","",Empleados!$B$14) | C16: =IF(Empleados!$A$14="","",Empleados!$C$14) | D16: =IF(Empleados!$A$14="",0,Empleados!$E$14*Configuracion!$C$14) -> 0 | E16: =IF(Empleados!$A$14="",0,INDEX(Bonificaciones!$B$14:$M$14,Configuracion!$C$14)*Configuracion!$C$14) -> 0 | F16: =D16+E16 -> 0 | G16: =F16*(Configuracion!$C$9+Configuracion!$C$10) -> 0 | H16: =F16-G16 -> 0
B17: TOTAL | D17: =SUM(D7:D16) -> 7600 | E17: =SUM(E7:E16) -> 350 | F17: =SUM(F7:F16) -> 7950 | G17: =SUM(G7:G16) -> 1669.5 | H17: =SUM(H7:H16) -> 6280.5
B18: N° de colaboradores activos | D18: =COUNTIF(Empleados!$A$5:$A$14,"<>") -> 5
B21: EVOLUCIÓN MENSUAL DE LA PLANILLA
B22: Mes | C22: Planilla bruta | D22: Descuentos | E22: Planilla neta
B23: Enero | C23: =(SUM(Empleados!$E$5:$E$14)+SUM(Bonificaciones!B$5:B$14))*Configuracion!$C$14 -> 7950 | D23: =C23*(Configuracion!$C$9+Configuracion!$C$10) -> 1669.5 | E23: =C23-D23 -> 6280.5
B24: Febrero | C24: =(SUM(Empleados!$E$5:$E$14)+SUM(Bonificaciones!C$5:C$14))*Configuracion!$C$14 -> 7920 | D24: =C24*(Configuracion!$C$9+Configuracion!$C$10) -> 1663.2 | E24: =C24-D24 -> 6256.8
B25: Marzo | C25: =(SUM(Empleados!$E$5:$E$14)+SUM(Bonificaciones!D$5:D$14))*Configuracion!$C$14 -> 8180 | D25: =C25*(Configuracion!$C$9+Configuracion!$C$10) -> 1717.8 | E25: =C25-D25 -> 6462.2
B26: Abril | C26: =(SUM(Empleados!$E$5:$E$14)+SUM(Bonificaciones!E$5:E$14))*Configuracion!$C$14 -> 7600 | D26: =C26*(Configuracion!$C$9+Configuracion!$C$10) -> 1596 | E26: =C26-D26 -> 6004
B27: Mayo | C27: =(SUM(Empleados!$E$5:$E$14)+SUM(Bonificaciones!F$5:F$14))*Configuracion!$C$14 -> 7600 | D27: =C27*(Configuracion!$C$9+Configuracion!$C$10) -> 1596 | E27: =C27-D27 -> 6004
B28: Junio | C28: =(SUM(Empleados!$E$5:$E$14)+SUM(Bonificaciones!G$5:G$14))*Configuracion!$C$14 -> 7800 | D28: =C28*(Configuracion!$C$9+Configuracion!$C$10) -> 1638 | E28: =C28-D28 -> 6162
B29: Julio | C29: =(SUM(Empleados!$E$5:$E$14)+SUM(Bonificaciones!H$5:H$14))*Configuracion!$C$14 -> 7600 | D29: =C29*(Configuracion!$C$9+Configuracion!$C$10) -> 1596 | E29: =C29-D29 -> 6004
B30: Agosto | C30: =(SUM(Empleados!$E$5:$E$14)+SUM(Bonificaciones!I$5:I$14))*Configuracion!$C$14 -> 7600 | D30: =C30*(Configuracion!$C$9+Configuracion!$C$10) -> 1596 | E30: =C30-D30 -> 6004
B31: Septiembre | C31: =(SUM(Empleados!$E$5:$E$14)+SUM(Bonificaciones!J$5:J$14))*Configuracion!$C$14 -> 8000 | D31: =C31*(Configuracion!$C$9+Configuracion!$C$10) -> 1680 | E31: =C31-D31 -> 6320
B32: Octubre | C32: =(SUM(Empleados!$E$5:$E$14)+SUM(Bonificaciones!K$5:K$14))*Configuracion!$C$14 -> 7600 | D32: =C32*(Configuracion!$C$9+Configuracion!$C$10) -> 1596 | E32: =C32-D32 -> 6004
B33: Noviembre | C33: =(SUM(Empleados!$E$5:$E$14)+SUM(Bonificaciones!L$5:L$14))*Configuracion!$C$14 -> 7600 | D33: =C33*(Configuracion!$C$9+Configuracion!$C$10) -> 1596 | E33: =C33-D33 -> 6004
B34: Diciembre | C34: =(SUM(Empleados!$E$5:$E$14)+SUM(Bonificaciones!M$5:M$14))*Configuracion!$C$14 -> 8950 | D34: =C34*(Configuracion!$C$9+Configuracion!$C$10) -> 1879.5 | E34: =C34-D34 -> 7070.5

Sheet Dashboard
B2: DASHBOARD · NÓMINA BÁSICA
B3: =" Mes: " & Configuracion!$C$11 & " | Moneda: " & Configuracion!$C$8 -> Mes: Enero | Moneda: Local
B5: PLANILLA BRUTA (MES) | D5: DESCUENTOS (MES) | F5: PLANILLA NETA (MES) | H5: N° COLABORADORES
B6: =Configuracion!$C$15&" "&TEXT(Resumen!F17,"#,##0.00") -> S/ 7,950.00 | D6: =Configuracion!$C$15&" "&TEXT(Resumen!G17,"#,##0.00") -> S/ 1,669.50 | F6: =Configuracion!$C$15&" "&TEXT(Resumen!H17,"#,##0.00") -> S/ 6,280.50 | H6: =Resumen!D18 -> 5
