Workbook

Sheet Portada
B2: LÍNEA DE PRODUCTOS DIGITALES · PLANTILLAS EXCEL
B4: CONTROL DE GASTOS PERSONALES
B7: Plantilla profesional para registrar tus ingresos y gastos, visualizar tu balance mensual y controlar tus finanzas personales — con panel de control, gráficos automáticos y selector de moneda (local / USD).
B10: QUÉ INCLUYE ESTA PLANTILLA
B11: ✔ Dashboard con indicadores clave (KPIs) y gráficos automáticos
B12: ✔ Fórmulas automáticas: nada que calcular a mano
B13: ✔ Gráficos: pastel, barras y tendencia mensual
B14: ✔ Resumen dinámico tipo tabla dinámica por categoría y por mes
B15: ✔ Listas desplegables y validación de datos en cada registro
B16: ✔ Selector de moneda: local o USD, con tipo de cambio editable
B17: ✔ Hoja de instrucciones paso a paso
B18: ✔ Celdas y fórmulas protegidas: solo editas donde debes
... B24: © Tu Marca de Plantillas · www.tumarca.com

Sheet Instrucciones
B2: CÓMO USAR ESTA PLANTILLA
B4: 1. Configuración
B5: Ve a la hoja 'Configuración' y define el símbolo de tu moneda local, su nombre y el tipo de cambio frente al USD. Ahí mismo eliges si el resto de la plantilla se muestra en moneda LOCAL o en USD.
B7: 2. Categorías
B8: En la hoja 'Categorías' puedes revisar o editar la lista de categorías de ingreso/gasto y los métodos de pago que aparecen como listas desplegables en 'Transacciones'.
B10: 3. Registrar movimientos
B11: En la hoja 'Transacciones' registra cada ingreso o gasto: fecha, categoría (lista desplegable), tipo, descripción, método de pago (lista desplegable) y monto en tu moneda local. La columna 'Monto en moneda seleccionada' se calcula sola.
B13: 4. Resumen automático
B14: La hoja 'Resumen' agrupa automáticamente tus movimientos por categoría y por mes, como una tabla dinámica, sin que tengas que hacer nada manualmente.
B16: 5. Dashboard
B17: La hoja 'Dashboard' muestra tus indicadores clave (ingresos, gastos, balance, tasa de ahorro) y tres gráficos que se actualizan solos cada vez que agregas movimientos.
B19: 6. Cambiar de moneda
... B28: Soporte y otras plantillas de esta línea de productos: www.tumarca.com

Sheet Configuracion
B2: CONFIGURACIÓN Y MONEDA
B4: Parámetro | C4: Valor | D4: Notas
B5: Nombre de moneda local | C5: Soles (PEN) | D5: Solo referencia. Escribe el nombre de tu moneda.
B6: Símbolo de moneda local | C6: S/ | D6: Símbolo que se usará en el Dashboard cuando la vista esté en LOCAL.
B7: Tipo de cambio (1 USD =) | C7: 3.75 | D7: Cuántas unidades de tu moneda local equivalen a 1 USD. Edítalo cuando cambie.
B8: Moneda de visualización | C8: Local | D8: Elige LOCAL o USD en la lista desplegable. Afecta Transacciones, Resumen y Dashboard.
B9: Año de análisis | C9: 2026 | D9: Año que se usa para agrupar el Resumen Mensual.
B11: Valores calculados (no editar)
B12: Factor de conversión aplicado | C12: =IF(C8="USD",1/C7,1) -> 1 | D12: Vale 1 si vista LOCAL; vale 1/Tipo de cambio si vista USD.
B13: Símbolo de moneda actual | C13: =IF(C8="USD","US$",C6) -> S/ | D13: Símbolo que verás en el Dashboard según la moneda elegida.
B15: Cambia 'Moneda de visualización' entre Local y USD para recalcular automáticamente toda la plantilla.

Sheet Categorias
B2: CATEGORÍAS Y MÉTODOS DE PAGO
B4: Categoría (ingreso/gasto) | C4: Método de pago
B5: Salario | C5: Efectivo
B6: Freelance / Ingresos extra | C6: Tarjeta de débito
B7: Otros ingresos | C7: Tarjeta de crédito
B8: Vivienda (alquiler/hipoteca) | C8: Transferencia bancaria
B9: Alimentación
B10: Transporte
B11: Servicios (luz, agua, internet)
B12: Salud
B13: Educación
B14: Entretenimiento
B15: Ropa y cuidado personal
B16: Ahorro e inversión
B17: Deudas y préstamos
B18: Otros gastos
B20: Puedes renombrar o agregar categorías/métodos aquí; las listas desplegables de 'Transacciones' se actualizan solas.

Sheet Transacciones
A2: REGISTRO DE INGRESOS Y GASTOS
A3: Completa las columnas A a F para cada movimiento. La columna G se calcula automáticamente.
A4: Fecha | B4: Categoría | C4: Tipo | D4: Descripción | E4: Método de pago | F4: Monto (moneda local) | G4: Monto (moneda seleccionada)
A5: 46025 | B5: Salario | C5: Ingreso | D5: Sueldo mensual | E5: Transferencia bancaria | F5: 4500 | G5: =IF(F5="","",F5*Configuracion!$C$12) -> 4500
A6: 46027 | B6: Vivienda (alquiler/hipoteca) | C6: Gasto | D6: Alquiler de enero | E6: Transferencia bancaria | F6: 1200 | G6: =IF(F6="","",F6*Configuracion!$C$12) -> 1200
A7: 46028 | B7: Alimentación | C7: Gasto | D7: Supermercado semanal | E7: Tarjeta de débito | F7: 180 | G7: =IF(F7="","",F7*Configuracion!$C$12) -> 180
A8: 46030 | B8: Transporte | C8: Gasto | D8: Gasolina | E8: Tarjeta de crédito | F8: 60 | G8: =IF(F8="","",F8*Configuracion!$C$12) -> 60
A9: 46032 | B9: Servicios (luz, agua, internet) | C9: Gasto | D9: Recibo de electricidad | E9: Transferencia bancaria | F9: 75 | G9: =IF(F9="","",F9*Configuracion!$C$12) -> 75
A10: 46034 | B10: Freelance / Ingresos extra | C10: Ingreso | D10: Proyecto de diseño | E10: Transferencia bancaria | F10: 350 | G10: =IF(F10="","",F10*Configuracion!$C$12) -> 350
A11: 46037 | B11: Entretenimiento | C11: Gasto | D11: Cine y cena | E11: Efectivo | F11: 45 | G11: =IF(F11="","",F11*Configuracion!$C$12) -> 45
A12: 46042 | B12: Salud | C12: Gasto | D12: Consulta médica | E12: Efectivo | F12: 90 | G12: =IF(F12="","",F12*Configuracion!$C$12) -> 90
A13: 46047 | B13: Ahorro e inversión | C13: Gasto | D13: Aporte a fondo de ahorro | E13: Transferencia bancaria | F13: 300 | G13: =IF(F13="","",F13*Configuracion!$C$12) -> 300
A14: 46056 | B14: Salario | C14: Ingreso | D14: Sueldo mensual | E14: Transferencia bancaria | F14: 4500 | G14: =IF(F14="","",F14*Configuracion!$C$12) -> 4500
A15: 46058 | B15: Vivienda (alquiler/hipoteca) | C15: Gasto | D15: Alquiler de febrero | E15: Transferencia bancaria | F15: 1200 | G15: =IF(F15="","",F15*Configuracion!$C$12) -> 1200
A16: 46060 | B16: Alimentación | C16: Gasto | D16: Supermercado semanal | E16: Tarjeta de débito | F16: 210 | G16: =IF(F16="","",F16*Configuracion!$C$12) -> 210
... A24: 46096 | B24: Deudas y préstamos | C24: Gasto | D24: Cuota de préstamo | E24: Transferencia bancaria | F24: 250 | G24: =IF(F24="","",F24*Configuracion!$C$12) -> 250
G25: =IF(F25="","",F25*Configuracion!$C$12)
G26: =IF(F26="","",F26*Configuracion!$C$12)
G27: =IF(F27="","",F27*Configuracion!$C$12)
G28: =IF(F28="","",F28*Configuracion!$C$12)
G29: =IF(F29="","",F29*Configuracion!$C$12)
G30: =IF(F30="","",F30*Configuracion!$C$12)
G31: =IF(F31="","",F31*Configuracion!$C$12)
G32: =IF(F32="","",F32*Configuracion!$C$12)
G33: =IF(F33="","",F33*Configuracion!$C$12)
G34: =IF(F34="","",F34*Configuracion!$C$12)
G35: =IF(F35="","",F35*Configuracion!$C$12)
G36: =IF(F36="","",F36*Configuracion!$C$12)
... G200: =IF(F200="","",F200*Configuracion!$C$12)

Sheet Resumen
B2: RESUMEN DINÁMICO (se actualiza solo)
B3: Tablas de resumen automáticas por categoría y por mes, equivalentes a una tabla dinámica, calculadas con fórmulas.
B5: RESUMEN POR CATEGORÍA
B6: Categoría | C6: Ingresos | D6: Gastos | E6: Neto
B7: =Categorias!$B$5 -> Salario | C7: =SUMIFS(Transacciones!$G$5:$G$200,Transacciones!$B$5:$B$200,$B7,Transacciones!$C$5:$C$200,"Ingreso") -> 13600 | D7: =SUMIFS(Transacciones!$G$5:$G$200,Transacciones!$B$5:$B$200,$B7,Transacciones!$C$5:$C$200,"Gasto") -> 0 | E7: =C7-D7 -> 13600
B8: =Categorias!$B$6 -> Freelance / Ingresos extra | C8: =SUMIFS(Transacciones!$G$5:$G$200,Transacciones!$B$5:$B$200,$B8,Transacciones!$C$5:$C$200,"Ingreso") -> 350 | D8: =SUMIFS(Transacciones!$G$5:$G$200,Transacciones!$B$5:$B$200,$B8,Transacciones!$C$5:$C$200,"Gasto") -> 0 | E8: =C8-D8 -> 350
B9: =Categorias!$B$7 -> Otros ingresos | C9: =SUMIFS(Transacciones!$G$5:$G$200,Transacciones!$B$5:$B$200,$B9,Transacciones!$C$5:$C$200,"Ingreso") -> 150 | D9: =SUMIFS(Transacciones!$G$5:$G$200,Transacciones!$B$5:$B$200,$B9,Transacciones!$C$5:$C$200,"Gasto") -> 0 | E9: =C9-D9 -> 150
B10: =Categorias!$B$8 -> Vivienda (alquiler/hipoteca) | C10: =SUMIFS(Transacciones!$G$5:$G$200,Transacciones!$B$5:$B$200,$B10,Transacciones!$C$5:$C$200,"Ingreso") -> 0 | D10: =SUMIFS(Transacciones!$G$5:$G$200,Transacciones!$B$5:$B$200,$B10,Transacciones!$C$5:$C$200,"Gasto") -> 3600 | E10: =C10-D10 -> -3600
B11: =Categorias!$B$9 -> Alimentación | C11: =SUMIFS(Transacciones!$G$5:$G$200,Transacciones!$B$5:$B$200,$B11,Transacciones!$C$5:$C$200,"Ingreso") -> 0 | D11: =SUMIFS(Transacciones!$G$5:$G$200,Transacciones!$B$5:$B$200,$B11,Transacciones!$C$5:$C$200,"Gasto") -> 585 | E11: =C11-D11 -> -585
B12: =Categorias!$B$10 -> Transporte | C12: =SUMIFS(Transacciones!$G$5:$G$200,Transacciones!$B$5:$B$200,$B12,Transacciones!$C$5:$C$200,"Ingreso") -> 0 | D12: =SUMIFS(Transacciones!$G$5:$G$200,Transacciones!$B$5:$B$200,$B12,Transacciones!$C$5:$C$200,"Gasto") -> 180 | E12: =C12-D12 -> -180
B13: =Categorias!$B$11 -> Servicios (luz, agua, internet) | C13: =SUMIFS(Transacciones!$G$5:$G$200,Transacciones!$B$5:$B$200,$B13,Transacciones!$C$5:$C$200,"Ingreso") -> 0 | D13: =SUMIFS(Transacciones!$G$5:$G$200,Transacciones!$B$5:$B$200,$B13,Transacciones!$C$5:$C$200,"Gasto") -> 75 | E13: =C13-D13 -> -75
B14: =Categorias!$B$12 -> Salud | C14: =SUMIFS(Transacciones!$G$5:$G$200,Transacciones!$B$5:$B$200,$B14,Transacciones!$C$5:$C$200,"Ingreso") -> 0 | D14: =SUMIFS(Transacciones!$G$5:$G$200,Transacciones!$B$5:$B$200,$B14,Transacciones!$C$5:$C$200,"Gasto") -> 90 | E14: =C14-D14 -> -90
B15: =Categorias!$B$13 -> Educación | C15: =SUMIFS(Transacciones!$G$5:$G$200,Transacciones!$B$5:$B$200,$B15,Transacciones!$C$5:$C$200,"Ingreso") -> 0 | D15: =SUMIFS(Transacciones!$G$5:$G$200,Transacciones!$B$5:$B$200,$B15,Transacciones!$C$5:$C$200,"Gasto") -> 80 | E15: =C15-D15 -> -80
B16: =Categorias!$B$14 -> Entretenimiento | C16: =SUMIFS(Transacciones!$G$5:$G$200,Transacciones!$B$5:$B$200,$B16,Transacciones!$C$5:$C$200,"Ingreso") -> 0 | D16: =SUMIFS(Transacciones!$G$5:$G$200,Transacciones!$B$5:$B$200,$B16,Transacciones!$C$5:$C$200,"Gasto") -> 70 | E16: =C16-D16 -> -70
B17: =Categorias!$B$15 -> Ropa y cuidado personal | C17: =SUMIFS(Transacciones!$G$5:$G$200,Transacciones!$B$5:$B$200,$B17,Transacciones!$C$5:$C$200,"Ingreso") -> 0 | D17: =SUMIFS(Transacciones!$G$5:$G$200,Transacciones!$B$5:$B$200,$B17,Transacciones!$C$5:$C$200,"Gasto") -> 0 | E17: =C17-D17 -> 0
B18: =Categorias!$B$16 -> Ahorro e inversión | C18: =SUMIFS(Transacciones!$G$5:$G$200,Transacciones!$B$5:$B$200,$B18,Transacciones!$C$5:$C$200,"Ingreso") -> 0 | D18: =SUMIFS(Transacciones!$G$5:$G$200,Transacciones!$B$5:$B$200,$B18,Transacciones!$C$5:$C$200,"Gasto") -> 300 | E18: =C18-D18 -> -300
B19: =Categorias!$B$17 -> Deudas y préstamos | C19: =SUMIFS(Transacciones!$G$5:$G$200,Transacciones!$B$5:$B$200,$B19,Transacciones!$C$5:$C$200,"Ingreso") -> 0 | D19: =SUMIFS(Transacciones!$G$5:$G$200,Transacciones!$B$5:$B$200,$B19,Transacciones!$C$5:$C$200,"Gasto") -> 250 | E19: =C19-D19 -> -250
B20: =Categorias!$B$18 -> Otros gastos | C20: =SUMIFS(Transacciones!$G$5:$G$200,Transacciones!$B$5:$B$200,$B20,Transacciones!$C$5:$C$200,"Ingreso") -> 0 | D20: =SUMIFS(Transacciones!$G$5:$G$200,Transacciones!$B$5:$B$200,$B20,Transacciones!$C$5:$C$200,"Gasto") -> 0 | E20: =C20-D20 -> 0
B21: TOTAL | C21: =SUM(C7:C20) -> 14100 | D21: =SUM(D7:D20) -> 5230 | E21: =SUM(E7:E20) -> 8870
B24: RESUMEN MENSUAL
B25: Mes | C25: Ingresos | D25: Gastos | E25: Ahorro neto | F25: % Ahorro
B26: Enero | C26: =SUMIFS(Transacciones!$G$5:$G$200,Transacciones!$C$5:$C$200,"Ingreso",Transacciones!$A$5:$A$200,">="&DATE(Configuracion!$C$9,1,1),Transacciones!$A$5:$A$200,"<="&EOMONTH(DATE(Configuracion!$C$9,1,1),0)) -> 4850 | D26: =SUMIFS(Transacciones!$G$5:$G$200,Transacciones!$C$5:$C$200,"Gasto",Transacciones!$A$5:$A$200,">="&DATE(Configuracion!$C$9,1,1),Transacciones!$A$5:$A$200,"<="&EOMONTH(DATE(Configuracion!$C$9,1,1),0)) -> 1950 | E26: =C26-D26 -> 2900 | F26: =IF(C26=0,0,E26/C26) -> 0.59793814
B27: Febrero | C27: =SUMIFS(Transacciones!$G$5:$G$200,Transacciones!$C$5:$C$200,"Ingreso",Transacciones!$A$5:$A$200,">="&DATE(Configuracion!$C$9,2,1),Transacciones!$A$5:$A$200,"<="&EOMONTH(DATE(Configuracion!$C$9,2,1),0)) -> 4650 | D27: =SUMIFS(Transacciones!$G$5:$G$200,Transacciones!$C$5:$C$200,"Gasto",Transacciones!$A$5:$A$200,">="&DATE(Configuracion!$C$9,2,1),Transacciones!$A$5:$A$200,"<="&EOMONTH(DATE(Configuracion!$C$9,2,1),0)) -> 1635 | E27: =C27-D27 -> 3015 | F27: =IF(C27=0,0,E27/C27) -> 0.6483871
B28: Marzo | C28: =SUMIFS(Transacciones!$G$5:$G$200,Transacciones!$C$5:$C$200,"Ingreso",Transacciones!$A$5:$A$200,">="&DATE(Configuracion!$C$9,3,1),Transacciones!$A$5:$A$200,"<="&EOMONTH(DATE(Configuracion!$C$9,3,1),0)) -> 4600 | D28: =SUMIFS(Transacciones!$G$5:$G$200,Transacciones!$C$5:$C$200,"Gasto",Transacciones!$A$5:$A$200,">="&DATE(Configuracion!$C$9,3,1),Transacciones!$A$5:$A$200,"<="&EOMONTH(DATE(Configuracion!$C$9,3,1),0)) -> 1645 | E28: =C28-D28 -> 2955 | F28: =IF(C28=0,0,E28/C28) -> 0.6423913
B29: Abril | C29: =SUMIFS(Transacciones!$G$5:$G$200,Transacciones!$C$5:$C$200,"Ingreso",Transacciones!$A$5:$A$200,">="&DATE(Configuracion!$C$9,4,1),Transacciones!$A$5:$A$200,"<="&EOMONTH(DATE(Configuracion!$C$9,4,1),0)) -> 0 | D29: =SUMIFS(Transacciones!$G$5:$G$200,Transacciones!$C$5:$C$200,"Gasto",Transacciones!$A$5:$A$200,">="&DATE(Configuracion!$C$9,4,1),Transacciones!$A$5:$A$200,"<="&EOMONTH(DATE(Configuracion!$C$9,4,1),0)) -> 0 | E29: =C29-D29 -> 0 | F29: =IF(C29=0,0,E29/C29) -> 0
B30: Mayo | C30: =SUMIFS(Transacciones!$G$5:$G$200,Transacciones!$C$5:$C$200,"Ingreso",Transacciones!$A$5:$A$200,">="&DATE(Configuracion!$C$9,5,1),Transacciones!$A$5:$A$200,"<="&EOMONTH(DATE(Configuracion!$C$9,5,1),0)) -> 0 | D30: =SUMIFS(Transacciones!$G$5:$G$200,Transacciones!$C$5:$C$200,"Gasto",Transacciones!$A$5:$A$200,">="&DATE(Configuracion!$C$9,5,1),Transacciones!$A$5:$A$200,"<="&EOMONTH(DATE(Configuracion!$C$9,5,1),0)) -> 0 | E30: =C30-D30 -> 0 | F30: =IF(C30=0,0,E30/C30) -> 0
B31: Junio | C31: =SUMIFS(Transacciones!$G$5:$G$200,Transacciones!$C$5:$C$200,"Ingreso",Transacciones!$A$5:$A$200,">="&DATE(Configuracion!$C$9,6,1),Transacciones!$A$5:$A$200,"<="&EOMONTH(DATE(Configuracion!$C$9,6,1),0)) -> 0 | D31: =SUMIFS(Transacciones!$G$5:$G$200,Transacciones!$C$5:$C$200,"Gasto",Transacciones!$A$5:$A$200,">="&DATE(Configuracion!$C$9,6,1),Transacciones!$A$5:$A$200,"<="&EOMONTH(DATE(Configuracion!$C$9,6,1),0)) -> 0 | E31: =C31-D31 -> 0 | F31: =IF(C31=0,0,E31/C31) -> 0
B32: Julio | C32: =SUMIFS(Transacciones!$G$5:$G$200,Transacciones!$C$5:$C$200,"Ingreso",Transacciones!$A$5:$A$200,">="&DATE(Configuracion!$C$9,7,1),Transacciones!$A$5:$A$200,"<="&EOMONTH(DATE(Configuracion!$C$9,7,1),0)) -> 0 | D32: =SUMIFS(Transacciones!$G$5:$G$200,Transacciones!$C$5:$C$200,"Gasto",Transacciones!$A$5:$A$200,">="&DATE(Configuracion!$C$9,7,1),Transacciones!$A$5:$A$200,"<="&EOMONTH(DATE(Configuracion!$C$9,7,1),0)) -> 0 | E32: =C32-D32 -> 0 | F32: =IF(C32=0,0,E32/C32) -> 0
B33: Agosto | C33: =SUMIFS(Transacciones!$G$5:$G$200,Transacciones!$C$5:$C$200,"Ingreso",Transacciones!$A$5:$A$200,">="&DATE(Configuracion!$C$9,8,1),Transacciones!$A$5:$A$200,"<="&EOMONTH(DATE(Configuracion!$C$9,8,1),0)) -> 0 | D33: =SUMIFS(Transacciones!$G$5:$G$200,Transacciones!$C$5:$C$200,"Gasto",Transacciones!$A$5:$A$200,">="&DATE(Configuracion!$C$9,8,1),Transacciones!$A$5:$A$200,"<="&EOMONTH(DATE(Configuracion!$C$9,8,1),0)) -> 0 | E33: =C33-D33 -> 0 | F33: =IF(C33=0,0,E33/C33) -> 0
B34: Septiembre | C34: =SUMIFS(Transacciones!$G$5:$G$200,Transacciones!$C$5:$C$200,"Ingreso",Transacciones!$A$5:$A$200,">="&DATE(Configuracion!$C$9,9,1),Transacciones!$A$5:$A$200,"<="&EOMONTH(DATE(Configuracion!$C$9,9,1),0)) -> 0 | D34: =SUMIFS(Transacciones!$G$5:$G$200,Transacciones!$C$5:$C$200,"Gasto",Transacciones!$A$5:$A$200,">="&DATE(Configuracion!$C$9,9,1),Transacciones!$A$5:$A$200,"<="&EOMONTH(DATE(Configuracion!$C$9,9,1),0)) -> 0 | E34: =C34-D34 -> 0 | F34: =IF(C34=0,0,E34/C34) -> 0
B35: Octubre | C35: =SUMIFS(Transacciones!$G$5:$G$200,Transacciones!$C$5:$C$200,"Ingreso",Transacciones!$A$5:$A$200,">="&DATE(Configuracion!$C$9,10,1),Transacciones!$A$5:$A$200,"<="&EOMONTH(DATE(Configuracion!$C$9,10,1),0)) -> 0 | D35: =SUMIFS(Transacciones!$G$5:$G$200,Transacciones!$C$5:$C$200,"Gasto",Transacciones!$A$5:$A$200,">="&DATE(Configuracion!$C$9,10,1),Transacciones!$A$5:$A$200,"<="&EOMONTH(DATE(Configuracion!$C$9,10,1),0)) -> 0 | E35: =C35-D35 -> 0 | F35: =IF(C35=0,0,E35/C35) -> 0
B36: Noviembre | C36: =SUMIFS(Transacciones!$G$5:$G$200,Transacciones!$C$5:$C$200,"Ingreso",Transacciones!$A$5:$A$200,">="&DATE(Configuracion!$C$9,11,1),Transacciones!$A$5:$A$200,"<="&EOMONTH(DATE(Configuracion!$C$9,11,1),0)) -> 0 | D36: =SUMIFS(Transacciones!$G$5:$G$200,Transacciones!$C$5:$C$200,"Gasto",Transacciones!$A$5:$A$200,">="&DATE(Configuracion!$C$9,11,1),Transacciones!$A$5:$A$200,"<="&EOMONTH(DATE(Configuracion!$C$9,11,1),0)) -> 0 | E36: =C36-D36 -> 0 | F36: =IF(C36=0,0,E36/C36) -> 0
B37: Diciembre | C37: =SUMIFS(Transacciones!$G$5:$G$200,Transacciones!$C$5:$C$200,"Ingreso",Transacciones!$A$5:$A$200,">="&DATE(Configuracion!$C$9,12,1),Transacciones!$A$5:$A$200,"<="&EOMONTH(DATE(Configuracion!$C$9,12,1),0)) -> 0 | D37: =SUMIFS(Transacciones!$G$5:$G$200,Transacciones!$C$5:$C$200,"Gasto",Transacciones!$A$5:$A$200,">="&DATE(Configuracion!$C$9,12,1),Transacciones!$A$5:$A$200,"<="&EOMONTH(DATE(Configuracion!$C$9,12,1),0)) -> 0 | E37: =C37-D37 -> 0 | F37: =IF(C37=0,0,E37/C37) -> 0

Sheet Dashboard
B2: DASHBOARD · CONTROL DE GASTOS PERSONALES
B3: ="Moneda de visualización: " & Configuracion!$C$8 & " | Año: " & Configuracion!$C$9 -> Moneda de visualización: Local | Año: 2026
B5: TOTAL INGRESOS | D5: TOTAL GASTOS | F5: BALANCE NETO | H5: TASA DE AHORRO
B6: =Configuracion!$C$13&" "&TEXT(Resumen!C21,"#,##0.00") -> S/ 14,100.00 | D6: =Configuracion!$C$13&" "&TEXT(Resumen!D21,"#,##0.00") -> S/ 5,230.00 | F6: =Configuracion!$C$13&" "&TEXT(Resumen!E21,"#,##0.00") -> S/ 8,870.00 | H6: =IF(Resumen!C21=0,"0.0%",TEXT(Resumen!E21/Resumen!C21,"0.0%")) -> 62.9%
