Workbook

Sheet Portada
B2: LÍNEA DE PRODUCTOS DIGITALES · PLANTILLAS EXCEL
B4: CONTROL DE VENTAS
B7: Registra cada venta de tu negocio, controla qué productos se venden más, quiénes son tus mejores clientes y cuánto tienes pendiente de cobro — con panel de control, gráficos automáticos y selector de moneda (local / USD).
B10: QUÉ INCLUYE ESTA PLANTILLA
B11: ✔ Dashboard con indicadores clave (KPIs) y gráficos automáticos
B12: ✔ Fórmulas automáticas: nada que calcular a mano
B13: ✔ Gráficos: pastel (ventas por producto), barras (ventas por mes y top clientes)
B14: ✔ Resumen dinámico tipo tabla dinámica por producto, cliente y mes
B15: ✔ Control de cobros: pagado vs. pendiente
B16: ✔ Listas desplegables y validación de datos en cada registro
B17: ✔ Selector de moneda: local o USD, con tipo de cambio editable
B18: ✔ Hoja de instrucciones paso a paso
... B24: © Tu Marca de Plantillas · www.tumarca.com

Sheet Instrucciones
B2: CÓMO USAR ESTA PLANTILLA
B4: 1. Configuración
B5: Define el símbolo de tu moneda local, el tipo de cambio y si la plantilla se muestra en moneda LOCAL o USD.
B7: 2. Catálogo y Clientes
B8: En 'Catálogo' registra tus productos/servicios y su precio. En 'Clientes' registra tu cartera de clientes. Ambos alimentan las listas desplegables de 'Ventas'.
B10: 3. Ventas
B11: En 'Ventas' registra cada venta: fecha, cliente (lista desplegable), producto (lista desplegable), cantidad, método de pago y estado (Pagado/Pendiente). El precio unitario y el total se calculan solos.
B13: 4. Resumen automático
B14: La hoja 'Resumen' agrupa automáticamente tus ventas por producto, por cliente y por mes, como una tabla dinámica.
B16: 5. Dashboard
B17: La hoja 'Dashboard' muestra tus ventas del año, tu ticket promedio, lo pendiente de cobro y tu producto más vendido, con gráficos que se actualizan solos.
B19: 6. Cambiar de moneda
... B25: Soporte y otras plantillas de esta línea de productos: www.tumarca.com

Sheet Configuracion
B2: CONFIGURACIÓN Y MONEDA
B4: Parámetro | C4: Valor | D4: Notas
B5: Nombre de moneda local | C5: Soles (PEN) | D5: Solo referencia. Escribe el nombre de tu moneda.
B6: Símbolo de moneda local | C6: S/ | D6: Símbolo que se usará en el Dashboard cuando la vista esté en LOCAL.
B7: Tipo de cambio (1 USD =) | C7: 3.75 | D7: Cuántas unidades de tu moneda local equivalen a 1 USD.
B8: Moneda de visualización | C8: Local | D8: Elige LOCAL o USD. Afecta Resumen y Dashboard.
B9: Año de análisis | C9: 2026 | D9: Año que se usa para agrupar el Resumen Mensual.
B10: Valores calculados (no editar)
B11: Factor de conversión aplicado | C11: =IF(C8="USD",1/C7,1) -> 1 | D11: Vale 1 si vista LOCAL; vale 1/Tipo de cambio si vista USD.
B12: Símbolo de moneda actual | C12: =IF(C8="USD","US$",C6) -> S/ | D12: Símbolo que verás en el Dashboard según la moneda elegida.
B14: Cambia 'Moneda de visualización' entre Local y USD para recalcular automáticamente toda la plantilla.

Sheet Catalogo
A2: CATÁLOGO DE PRODUCTOS / SERVICIOS
A4: Producto / Servicio | B4: Categoría | C4: Precio unitario
A5: Consultoría por hora | B5: Servicios | C5: 45
A6: Diseño de logo | B6: Servicios | C6: 150
A7: Plantilla Excel básica | B7: Productos digitales | C7: 7
A8: Plantilla Excel avanzada | B8: Productos digitales | C8: 15
A9: Paquete de mantenimiento mensual | B9: Servicios | C9: 200
A10: Curso en línea | B10: Productos digitales | C10: 40

Sheet Clientes
A2: CARTERA DE CLIENTES
A4: Cliente | B4: Contacto
A5: María Fernández | B5: maria.f@email.com
A6: Carlos Rojas | B6: carlos.rojas@email.com
A7: Tienda El Sol S.A.C. | B7: ventas@elsol.com
A8: Laura Gómez | B8: laura.gomez@email.com
A9: Distribuidora Andina | B9: contacto@andina.com

Sheet Ventas
A2: REGISTRO DE VENTAS
A3: Completa las columnas A, B, C, D, G y H. El precio unitario y el total se calculan automáticamente.
A4: Fecha | B4: Cliente | C4: Producto / Servicio | D4: Cantidad | E4: Precio unitario | F4: Total | G4: Método de pago | H4: Estado
A5: 46027 | B5: María Fernández | C5: Plantilla Excel básica | D5: 1 | E5: =IF(C5="","",IFERROR(INDEX(Catalogo!$C$5:$C$12,MATCH(C5,Catalogo!$A$5:$A$12,0)),0)) -> 7 | F5: =IF(OR(C5="",D5=""),"",D5*E5) -> 7 | G5: Transferencia | H5: Pagado
A6: 46030 | B6: Carlos Rojas | C6: Consultoría por hora | D6: 3 | E6: =IF(C6="","",IFERROR(INDEX(Catalogo!$C$5:$C$12,MATCH(C6,Catalogo!$A$5:$A$12,0)),0)) -> 45 | F6: =IF(OR(C6="",D6=""),"",D6*E6) -> 135 | G6: Tarjeta | H6: Pagado
A7: 46034 | B7: Tienda El Sol S.A.C. | C7: Diseño de logo | D7: 1 | E7: =IF(C7="","",IFERROR(INDEX(Catalogo!$C$5:$C$12,MATCH(C7,Catalogo!$A$5:$A$12,0)),0)) -> 150 | F7: =IF(OR(C7="",D7=""),"",D7*E7) -> 150 | G7: Transferencia | H7: Pendiente
A8: 46040 | B8: Laura Gómez | C8: Plantilla Excel avanzada | D8: 2 | E8: =IF(C8="","",IFERROR(INDEX(Catalogo!$C$5:$C$12,MATCH(C8,Catalogo!$A$5:$A$12,0)),0)) -> 15 | F8: =IF(OR(C8="",D8=""),"",D8*E8) -> 30 | G8: Efectivo | H8: Pagado
A9: 46047 | B9: Distribuidora Andina | C9: Paquete de mantenimiento mensual | D9: 1 | E9: =IF(C9="","",IFERROR(INDEX(Catalogo!$C$5:$C$12,MATCH(C9,Catalogo!$A$5:$A$12,0)),0)) -> 200 | F9: =IF(OR(C9="",D9=""),"",D9*E9) -> 200 | G9: Transferencia | H9: Pagado
A10: 46055 | B10: María Fernández | C10: Curso en línea | D10: 1 | E10: =IF(C10="","",IFERROR(INDEX(Catalogo!$C$5:$C$12,MATCH(C10,Catalogo!$A$5:$A$12,0)),0)) -> 40 | F10: =IF(OR(C10="",D10=""),"",D10*E10) -> 40 | G10: Tarjeta | H10: Pagado
A11: 46059 | B11: Carlos Rojas | C11: Plantilla Excel básica | D11: 3 | E11: =IF(C11="","",IFERROR(INDEX(Catalogo!$C$5:$C$12,MATCH(C11,Catalogo!$A$5:$A$12,0)),0)) -> 7 | F11: =IF(OR(C11="",D11=""),"",D11*E11) -> 21 | G11: Efectivo | H11: Pagado
A12: 46067 | B12: Tienda El Sol S.A.C. | C12: Consultoría por hora | D12: 5 | E12: =IF(C12="","",IFERROR(INDEX(Catalogo!$C$5:$C$12,MATCH(C12,Catalogo!$A$5:$A$12,0)),0)) -> 45 | F12: =IF(OR(C12="",D12=""),"",D12*E12) -> 225 | G12: Transferencia | H12: Pendiente
A13: 46073 | B13: Laura Gómez | C13: Diseño de logo | D13: 1 | E13: =IF(C13="","",IFERROR(INDEX(Catalogo!$C$5:$C$12,MATCH(C13,Catalogo!$A$5:$A$12,0)),0)) -> 150 | F13: =IF(OR(C13="",D13=""),"",D13*E13) -> 150 | G13: Tarjeta | H13: Pagado
A14: 46084 | B14: Distribuidora Andina | C14: Paquete de mantenimiento mensual | D14: 1 | E14: =IF(C14="","",IFERROR(INDEX(Catalogo!$C$5:$C$12,MATCH(C14,Catalogo!$A$5:$A$12,0)),0)) -> 200 | F14: =IF(OR(C14="",D14=""),"",D14*E14) -> 200 | G14: Transferencia | H14: Pagado
A15: 46090 | B15: María Fernández | C15: Plantilla Excel avanzada | D15: 1 | E15: =IF(C15="","",IFERROR(INDEX(Catalogo!$C$5:$C$12,MATCH(C15,Catalogo!$A$5:$A$12,0)),0)) -> 15 | F15: =IF(OR(C15="",D15=""),"",D15*E15) -> 15 | G15: Efectivo | H15: Pagado
A16: 46096 | B16: Carlos Rojas | C16: Curso en línea | D16: 2 | E16: =IF(C16="","",IFERROR(INDEX(Catalogo!$C$5:$C$12,MATCH(C16,Catalogo!$A$5:$A$12,0)),0)) -> 40 | F16: =IF(OR(C16="",D16=""),"",D16*E16) -> 80 | G16: Tarjeta | H16: Pendiente
E17: =IF(C17="","",IFERROR(INDEX(Catalogo!$C$5:$C$12,MATCH(C17,Catalogo!$A$5:$A$12,0)),0)) | F17: =IF(OR(C17="",D17=""),"",D17*E17)
E18: =IF(C18="","",IFERROR(INDEX(Catalogo!$C$5:$C$12,MATCH(C18,Catalogo!$A$5:$A$12,0)),0)) | F18: =IF(OR(C18="",D18=""),"",D18*E18)
E19: =IF(C19="","",IFERROR(INDEX(Catalogo!$C$5:$C$12,MATCH(C19,Catalogo!$A$5:$A$12,0)),0)) | F19: =IF(OR(C19="",D19=""),"",D19*E19)
E20: =IF(C20="","",IFERROR(INDEX(Catalogo!$C$5:$C$12,MATCH(C20,Catalogo!$A$5:$A$12,0)),0)) | F20: =IF(OR(C20="",D20=""),"",D20*E20)
E21: =IF(C21="","",IFERROR(INDEX(Catalogo!$C$5:$C$12,MATCH(C21,Catalogo!$A$5:$A$12,0)),0)) | F21: =IF(OR(C21="",D21=""),"",D21*E21)
E22: =IF(C22="","",IFERROR(INDEX(Catalogo!$C$5:$C$12,MATCH(C22,Catalogo!$A$5:$A$12,0)),0)) | F22: =IF(OR(C22="",D22=""),"",D22*E22)
E23: =IF(C23="","",IFERROR(INDEX(Catalogo!$C$5:$C$12,MATCH(C23,Catalogo!$A$5:$A$12,0)),0)) | F23: =IF(OR(C23="",D23=""),"",D23*E23)
E24: =IF(C24="","",IFERROR(INDEX(Catalogo!$C$5:$C$12,MATCH(C24,Catalogo!$A$5:$A$12,0)),0)) | F24: =IF(OR(C24="",D24=""),"",D24*E24)
E25: =IF(C25="","",IFERROR(INDEX(Catalogo!$C$5:$C$12,MATCH(C25,Catalogo!$A$5:$A$12,0)),0)) | F25: =IF(OR(C25="",D25=""),"",D25*E25)
E26: =IF(C26="","",IFERROR(INDEX(Catalogo!$C$5:$C$12,MATCH(C26,Catalogo!$A$5:$A$12,0)),0)) | F26: =IF(OR(C26="",D26=""),"",D26*E26)
E27: =IF(C27="","",IFERROR(INDEX(Catalogo!$C$5:$C$12,MATCH(C27,Catalogo!$A$5:$A$12,0)),0)) | F27: =IF(OR(C27="",D27=""),"",D27*E27)
E28: =IF(C28="","",IFERROR(INDEX(Catalogo!$C$5:$C$12,MATCH(C28,Catalogo!$A$5:$A$12,0)),0)) | F28: =IF(OR(C28="",D28=""),"",D28*E28)
... E204: =IF(C204="","",IFERROR(INDEX(Catalogo!$C$5:$C$12,MATCH(C204,Catalogo!$A$5:$A$12,0)),0)) | F204: =IF(OR(C204="",D204=""),"",D204*E204)

Sheet Resumen
B2: RESUMEN DINÁMICO (se actualiza solo)
B3: =" Moneda: " & Configuracion!$C$8 -> Moneda: Local
B5: VENTAS POR PRODUCTO
B6: Producto / Servicio | C6: Unidades vendidas | D6: Total ventas
B7: =Catalogo!$A$5 -> Consultoría por hora | C7: =SUMIFS(Ventas!$D$5:$D$204,Ventas!$C$5:$C$204,$B7) -> 8 | D7: =SUMIFS(Ventas!$F$5:$F$204,Ventas!$C$5:$C$204,$B7)*Configuracion!$C$11 -> 360
B8: =Catalogo!$A$6 -> Diseño de logo | C8: =SUMIFS(Ventas!$D$5:$D$204,Ventas!$C$5:$C$204,$B8) -> 2 | D8: =SUMIFS(Ventas!$F$5:$F$204,Ventas!$C$5:$C$204,$B8)*Configuracion!$C$11 -> 300
B9: =Catalogo!$A$7 -> Plantilla Excel básica | C9: =SUMIFS(Ventas!$D$5:$D$204,Ventas!$C$5:$C$204,$B9) -> 4 | D9: =SUMIFS(Ventas!$F$5:$F$204,Ventas!$C$5:$C$204,$B9)*Configuracion!$C$11 -> 28
B10: =Catalogo!$A$8 -> Plantilla Excel avanzada | C10: =SUMIFS(Ventas!$D$5:$D$204,Ventas!$C$5:$C$204,$B10) -> 3 | D10: =SUMIFS(Ventas!$F$5:$F$204,Ventas!$C$5:$C$204,$B10)*Configuracion!$C$11 -> 45
B11: =Catalogo!$A$9 -> Paquete de mantenimiento mensual | C11: =SUMIFS(Ventas!$D$5:$D$204,Ventas!$C$5:$C$204,$B11) -> 2 | D11: =SUMIFS(Ventas!$F$5:$F$204,Ventas!$C$5:$C$204,$B11)*Configuracion!$C$11 -> 400
B12: =Catalogo!$A$10 -> Curso en línea | C12: =SUMIFS(Ventas!$D$5:$D$204,Ventas!$C$5:$C$204,$B12) -> 3 | D12: =SUMIFS(Ventas!$F$5:$F$204,Ventas!$C$5:$C$204,$B12)*Configuracion!$C$11 -> 120
B13: =Catalogo!$A$11 -> 0 | C13: =SUMIFS(Ventas!$D$5:$D$204,Ventas!$C$5:$C$204,$B13) -> 0 | D13: =SUMIFS(Ventas!$F$5:$F$204,Ventas!$C$5:$C$204,$B13)*Configuracion!$C$11 -> 0
B14: =Catalogo!$A$12 -> 0 | C14: =SUMIFS(Ventas!$D$5:$D$204,Ventas!$C$5:$C$204,$B14) -> 0 | D14: =SUMIFS(Ventas!$F$5:$F$204,Ventas!$C$5:$C$204,$B14)*Configuracion!$C$11 -> 0
B17: VENTAS POR CLIENTE
B18: Cliente | C18: Total comprado
B19: =Clientes!$A$5 -> María Fernández | C19: =SUMIFS(Ventas!$F$5:$F$204,Ventas!$B$5:$B$204,$B19)*Configuracion!$C$11 -> 62
B20: =Clientes!$A$6 -> Carlos Rojas | C20: =SUMIFS(Ventas!$F$5:$F$204,Ventas!$B$5:$B$204,$B20)*Configuracion!$C$11 -> 236
B21: =Clientes!$A$7 -> Tienda El Sol S.A.C. | C21: =SUMIFS(Ventas!$F$5:$F$204,Ventas!$B$5:$B$204,$B21)*Configuracion!$C$11 -> 375
B22: =Clientes!$A$8 -> Laura Gómez | C22: =SUMIFS(Ventas!$F$5:$F$204,Ventas!$B$5:$B$204,$B22)*Configuracion!$C$11 -> 180
B23: =Clientes!$A$9 -> Distribuidora Andina | C23: =SUMIFS(Ventas!$F$5:$F$204,Ventas!$B$5:$B$204,$B23)*Configuracion!$C$11 -> 400
B24: =Clientes!$A$10 -> 0 | C24: =SUMIFS(Ventas!$F$5:$F$204,Ventas!$B$5:$B$204,$B24)*Configuracion!$C$11 -> 0
B25: =Clientes!$A$11 -> 0 | C25: =SUMIFS(Ventas!$F$5:$F$204,Ventas!$B$5:$B$204,$B25)*Configuracion!$C$11 -> 0
B28: VENTAS MENSUALES
B29: Mes | C29: Total ventas | D29: N° de ventas
B30: Enero | C30: =SUMIFS(Ventas!$F$5:$F$204,Ventas!$A$5:$A$204,">="&DATE(Configuracion!$C$9,1,1),Ventas!$A$5:$A$204,"<="&EOMONTH(DATE(Configuracion!$C$9,1,1),0))*Configuracion!$C$11 -> 522 | D30: =COUNTIFS(Ventas!$A$5:$A$204,">="&DATE(Configuracion!$C$9,1,1),Ventas!$A$5:$A$204,"<="&EOMONTH(DATE(Configuracion!$C$9,1,1),0)) -> 5
B31: Febrero | C31: =SUMIFS(Ventas!$F$5:$F$204,Ventas!$A$5:$A$204,">="&DATE(Configuracion!$C$9,2,1),Ventas!$A$5:$A$204,"<="&EOMONTH(DATE(Configuracion!$C$9,2,1),0))*Configuracion!$C$11 -> 436 | D31: =COUNTIFS(Ventas!$A$5:$A$204,">="&DATE(Configuracion!$C$9,2,1),Ventas!$A$5:$A$204,"<="&EOMONTH(DATE(Configuracion!$C$9,2,1),0)) -> 4
B32: Marzo | C32: =SUMIFS(Ventas!$F$5:$F$204,Ventas!$A$5:$A$204,">="&DATE(Configuracion!$C$9,3,1),Ventas!$A$5:$A$204,"<="&EOMONTH(DATE(Configuracion!$C$9,3,1),0))*Configuracion!$C$11 -> 295 | D32: =COUNTIFS(Ventas!$A$5:$A$204,">="&DATE(Configuracion!$C$9,3,1),Ventas!$A$5:$A$204,"<="&EOMONTH(DATE(Configuracion!$C$9,3,1),0)) -> 3
B33: Abril | C33: =SUMIFS(Ventas!$F$5:$F$204,Ventas!$A$5:$A$204,">="&DATE(Configuracion!$C$9,4,1),Ventas!$A$5:$A$204,"<="&EOMONTH(DATE(Configuracion!$C$9,4,1),0))*Configuracion!$C$11 -> 0 | D33: =COUNTIFS(Ventas!$A$5:$A$204,">="&DATE(Configuracion!$C$9,4,1),Ventas!$A$5:$A$204,"<="&EOMONTH(DATE(Configuracion!$C$9,4,1),0)) -> 0
B34: Mayo | C34: =SUMIFS(Ventas!$F$5:$F$204,Ventas!$A$5:$A$204,">="&DATE(Configuracion!$C$9,5,1),Ventas!$A$5:$A$204,"<="&EOMONTH(DATE(Configuracion!$C$9,5,1),0))*Configuracion!$C$11 -> 0 | D34: =COUNTIFS(Ventas!$A$5:$A$204,">="&DATE(Configuracion!$C$9,5,1),Ventas!$A$5:$A$204,"<="&EOMONTH(DATE(Configuracion!$C$9,5,1),0)) -> 0
B35: Junio | C35: =SUMIFS(Ventas!$F$5:$F$204,Ventas!$A$5:$A$204,">="&DATE(Configuracion!$C$9,6,1),Ventas!$A$5:$A$204,"<="&EOMONTH(DATE(Configuracion!$C$9,6,1),0))*Configuracion!$C$11 -> 0 | D35: =COUNTIFS(Ventas!$A$5:$A$204,">="&DATE(Configuracion!$C$9,6,1),Ventas!$A$5:$A$204,"<="&EOMONTH(DATE(Configuracion!$C$9,6,1),0)) -> 0
B36: Julio | C36: =SUMIFS(Ventas!$F$5:$F$204,Ventas!$A$5:$A$204,">="&DATE(Configuracion!$C$9,7,1),Ventas!$A$5:$A$204,"<="&EOMONTH(DATE(Configuracion!$C$9,7,1),0))*Configuracion!$C$11 -> 0 | D36: =COUNTIFS(Ventas!$A$5:$A$204,">="&DATE(Configuracion!$C$9,7,1),Ventas!$A$5:$A$204,"<="&EOMONTH(DATE(Configuracion!$C$9,7,1),0)) -> 0
B37: Agosto | C37: =SUMIFS(Ventas!$F$5:$F$204,Ventas!$A$5:$A$204,">="&DATE(Configuracion!$C$9,8,1),Ventas!$A$5:$A$204,"<="&EOMONTH(DATE(Configuracion!$C$9,8,1),0))*Configuracion!$C$11 -> 0 | D37: =COUNTIFS(Ventas!$A$5:$A$204,">="&DATE(Configuracion!$C$9,8,1),Ventas!$A$5:$A$204,"<="&EOMONTH(DATE(Configuracion!$C$9,8,1),0)) -> 0
B38: Septiembre | C38: =SUMIFS(Ventas!$F$5:$F$204,Ventas!$A$5:$A$204,">="&DATE(Configuracion!$C$9,9,1),Ventas!$A$5:$A$204,"<="&EOMONTH(DATE(Configuracion!$C$9,9,1),0))*Configuracion!$C$11 -> 0 | D38: =COUNTIFS(Ventas!$A$5:$A$204,">="&DATE(Configuracion!$C$9,9,1),Ventas!$A$5:$A$204,"<="&EOMONTH(DATE(Configuracion!$C$9,9,1),0)) -> 0
B39: Octubre | C39: =SUMIFS(Ventas!$F$5:$F$204,Ventas!$A$5:$A$204,">="&DATE(Configuracion!$C$9,10,1),Ventas!$A$5:$A$204,"<="&EOMONTH(DATE(Configuracion!$C$9,10,1),0))*Configuracion!$C$11 -> 0 | D39: =COUNTIFS(Ventas!$A$5:$A$204,">="&DATE(Configuracion!$C$9,10,1),Ventas!$A$5:$A$204,"<="&EOMONTH(DATE(Configuracion!$C$9,10,1),0)) -> 0
B40: Noviembre | C40: =SUMIFS(Ventas!$F$5:$F$204,Ventas!$A$5:$A$204,">="&DATE(Configuracion!$C$9,11,1),Ventas!$A$5:$A$204,"<="&EOMONTH(DATE(Configuracion!$C$9,11,1),0))*Configuracion!$C$11 -> 0 | D40: =COUNTIFS(Ventas!$A$5:$A$204,">="&DATE(Configuracion!$C$9,11,1),Ventas!$A$5:$A$204,"<="&EOMONTH(DATE(Configuracion!$C$9,11,1),0)) -> 0
B41: Diciembre | C41: =SUMIFS(Ventas!$F$5:$F$204,Ventas!$A$5:$A$204,">="&DATE(Configuracion!$C$9,12,1),Ventas!$A$5:$A$204,"<="&EOMONTH(DATE(Configuracion!$C$9,12,1),0))*Configuracion!$C$11 -> 0 | D41: =COUNTIFS(Ventas!$A$5:$A$204,">="&DATE(Configuracion!$C$9,12,1),Ventas!$A$5:$A$204,"<="&EOMONTH(DATE(Configuracion!$C$9,12,1),0)) -> 0
B42: TOTAL | C42: =SUM(C30:C41) -> 1253 | D42: =SUM(D30:D41) -> 12
B44: Total pendiente de cobro | C44: =SUMIFS(Ventas!$F$5:$F$204,Ventas!$H$5:$H$204,"Pendiente")*Configuracion!$C$11 -> 455
B45: Ticket promedio | C45: =IF(D42=0,0,C42/D42) -> 104.41667
B46: Producto más vendido (por monto) | C46: =INDEX(B7:B14,MATCH(MAX(D7:D14),D7:D14,0)) -> Paquete de mantenimiento mensual

Sheet Dashboard
B2: DASHBOARD · CONTROL DE VENTAS
B3: =" Moneda: " & Configuracion!$C$8 & " | Año: " & Configuracion!$C$9 -> Moneda: Local | Año: 2026
B5: VENTAS DEL AÑO | D5: TICKET PROMEDIO | F5: PENDIENTE DE COBRO | H5: PRODUCTO TOP
B6: =Configuracion!$C$12&" "&TEXT(Resumen!C42,"#,##0.00") -> S/ 1,253.00 | D6: =Configuracion!$C$12&" "&TEXT(Resumen!C45,"#,##0.00") -> S/ 104.42 | F6: =Configuracion!$C$12&" "&TEXT(Resumen!C44,"#,##0.00") -> S/ 455.00 | H6: =Resumen!C46 -> Paquete de mantenimiento mensual
