Workbook

Sheet Portada
B2: LÍNEA DE PRODUCTOS DIGITALES · PLANTILLAS EXCEL
B4: PRESUPUESTO MENSUAL
B7: Planifica tus ingresos y gastos mes a mes, compara lo presupuestado contra lo real y visualiza tus desviaciones al instante — con panel de control, gráficos automáticos y selector de moneda (local / USD).
B10: QUÉ INCLUYE ESTA PLANTILLA
B11: ✔ Dashboard con indicadores clave (KPIs) y gráficos automáticos
B12: ✔ Fórmulas automáticas: nada que calcular a mano
B13: ✔ Gráficos: barras (presupuestado vs. real), tendencia anual y pastel
B14: ✔ Resumen dinámico tipo tabla dinámica por categoría y por mes
B15: ✔ Listas desplegables y validación de datos en cada registro
B16: ✔ Selector de moneda: local o USD, con tipo de cambio editable
B17: ✔ Hoja de instrucciones paso a paso
B18: ✔ Celdas y fórmulas protegidas: solo editas donde debes
... B24: © Tu Marca de Plantillas · www.tumarca.com

Sheet Instrucciones
B2: CÓMO USAR ESTA PLANTILLA
B4: 1. Configuración
B5: Ve a la hoja 'Configuración' y define el símbolo de tu moneda local, el tipo de cambio, el mes que quieres analizar y si el resto de la plantilla se muestra en moneda LOCAL o USD.
B7: 2. Categorías
B8: En la hoja 'Categorías' puedes revisar o editar las categorías de ingreso/gasto que se usan en 'Presupuesto' y 'Real'.
B10: 3. Presupuesto
B11: En la hoja 'Presupuesto' escribe cuánto planeas ingresar/gastar en cada categoría, mes a mes. La columna 'Total anual' se calcula sola.
B13: 4. Real
B14: En la hoja 'Real' registra lo que efectivamente ingresaste/gastaste cada mes, en las mismas categorías y meses que en 'Presupuesto'.
B16: 5. Resumen automático
B17: La hoja 'Resumen' compara Presupuestado vs. Real para el mes elegido en 'Configuración', categoría por categoría, y además totaliza los 12 meses del año, como una tabla dinámica.
B19: 6. Dashboard
... B28: Soporte y otras plantillas de esta línea de productos: www.tumarca.com

Sheet Configuracion
B2: CONFIGURACIÓN Y MONEDA
B4: Parámetro | C4: Valor | D4: Notas
B5: Nombre de moneda local | C5: Soles (PEN) | D5: Solo referencia. Escribe el nombre de tu moneda.
B6: Símbolo de moneda local | C6: S/ | D6: Símbolo que se usará en el Dashboard cuando la vista esté en LOCAL.
B7: Tipo de cambio (1 USD =) | C7: 3.75 | D7: Cuántas unidades de tu moneda local equivalen a 1 USD.
B8: Moneda de visualización | C8: Local | D8: Elige LOCAL o USD. Afecta Resumen y Dashboard.
B9: Año de análisis | C9: 2026 | D9: Año que se usa como referencia en Presupuesto y Real.
B10: Mes seleccionado | C10: Enero | D10: Mes que se muestra en Resumen y Dashboard.
B11: Valores calculados (no editar)
B12: Factor de conversión aplicado | C12: =IF(C8="USD",1/C7,1) -> 1 | D12: Vale 1 si vista LOCAL; vale 1/Tipo de cambio si vista USD.
B13: Símbolo de moneda actual | C13: =IF(C8="USD","US$",C6) -> S/ | D13: Símbolo que verás en el Dashboard según la moneda elegida.
B14: Número de mes seleccionado | C14: =MATCH(C10,{"Enero","Febrero","Marzo","Abril","Mayo","Junio","Julio","Agosto","Septiembre","Octubre","Noviembre","Diciembre"},0) -> 1 | D14: 1=Enero ... 12=Diciembre. Se usa para ubicar la columna del mes en Presupuesto y Real.
B16: Cambia 'Mes seleccionado' o 'Moneda de visualización' para recalcular automáticamente Resumen y Dashboard.

Sheet Categorias
B2: CATEGORÍAS DE PRESUPUESTO
B4: Categoría (ingreso/gasto)
B5: Salario
B6: Freelance / Ingresos extra
B7: Otros ingresos
B8: Vivienda (alquiler/hipoteca)
B9: Alimentación
B10: Transporte
B11: Servicios (luz, agua, internet)
B12: Salud
B13: Educación
B14: Entretenimiento
... B20: Estas categorías deben coincidir, en el mismo orden, con las filas de 'Presupuesto' y 'Real'.

Sheet Presupuesto
A2: PRESUPUESTO ANUAL (por categoría y mes)
A4: Categoría | B4: Ene | C4: Feb | D4: Mar | E4: Abr | F4: May | G4: Jun | H4: Jul | I4: Ago | J4: Sep | K4: Oct | L4: Nov | M4: Dic | N4: Total anual
A5: =Categorias!$B$5 -> Salario | B5: 4500 | C5: 4500 | D5: 4500 | E5: 4500 | F5: 4500 | G5: 4500 | H5: 4500 | I5: 4500 | J5: 4500 | K5: 4500 | L5: 4500 | M5: 4500 | N5: =SUM(B5:M5) -> 54000
A6: =Categorias!$B$6 -> Freelance / Ingresos extra | B6: 300 | C6: 300 | D6: 300 | E6: 300 | F6: 300 | G6: 300 | H6: 300 | I6: 300 | J6: 300 | K6: 300 | L6: 300 | M6: 300 | N6: =SUM(B6:M6) -> 3600
A7: =Categorias!$B$7 -> Otros ingresos | B7: 0 | C7: 0 | D7: 0 | E7: 0 | F7: 0 | G7: 0 | H7: 0 | I7: 0 | J7: 0 | K7: 0 | L7: 0 | M7: 0 | N7: =SUM(B7:M7) -> 0
A8: =Categorias!$B$8 -> Vivienda (alquiler/hipoteca) | B8: 1200 | C8: 1200 | D8: 1200 | E8: 1200 | F8: 1200 | G8: 1200 | H8: 1200 | I8: 1200 | J8: 1200 | K8: 1200 | L8: 1200 | M8: 1200 | N8: =SUM(B8:M8) -> 14400
A9: =Categorias!$B$9 -> Alimentación | B9: 200 | C9: 200 | D9: 200 | E9: 200 | F9: 200 | G9: 200 | H9: 200 | I9: 200 | J9: 200 | K9: 200 | L9: 200 | M9: 200 | N9: =SUM(B9:M9) -> 2400
A10: =Categorias!$B$10 -> Transporte | B10: 100 | C10: 100 | D10: 100 | E10: 100 | F10: 100 | G10: 100 | H10: 100 | I10: 100 | J10: 100 | K10: 100 | L10: 100 | M10: 100 | N10: =SUM(B10:M10) -> 1200
A11: =Categorias!$B$11 -> Servicios (luz, agua, internet) | B11: 80 | C11: 80 | D11: 80 | E11: 80 | F11: 80 | G11: 80 | H11: 80 | I11: 80 | J11: 80 | K11: 80 | L11: 80 | M11: 80 | N11: =SUM(B11:M11) -> 960
A12: =Categorias!$B$12 -> Salud | B12: 60 | C12: 60 | D12: 60 | E12: 60 | F12: 60 | G12: 60 | H12: 60 | I12: 60 | J12: 60 | K12: 60 | L12: 60 | M12: 60 | N12: =SUM(B12:M12) -> 720
A13: =Categorias!$B$13 -> Educación | B13: 80 | C13: 80 | D13: 80 | E13: 80 | F13: 80 | G13: 80 | H13: 80 | I13: 80 | J13: 80 | K13: 80 | L13: 80 | M13: 80 | N13: =SUM(B13:M13) -> 960
A14: =Categorias!$B$14 -> Entretenimiento | B14: 60 | C14: 60 | D14: 60 | E14: 60 | F14: 60 | G14: 60 | H14: 60 | I14: 60 | J14: 60 | K14: 60 | L14: 60 | M14: 60 | N14: =SUM(B14:M14) -> 720
A15: =Categorias!$B$15 -> Ropa y cuidado personal | B15: 50 | C15: 50 | D15: 50 | E15: 50 | F15: 50 | G15: 50 | H15: 50 | I15: 50 | J15: 50 | K15: 50 | L15: 50 | M15: 50 | N15: =SUM(B15:M15) -> 600
A16: =Categorias!$B$16 -> Ahorro e inversión | B16: 300 | C16: 300 | D16: 300 | E16: 300 | F16: 300 | G16: 300 | H16: 300 | I16: 300 | J16: 300 | K16: 300 | L16: 300 | M16: 300 | N16: =SUM(B16:M16) -> 3600
A17: =Categorias!$B$17 -> Deudas y préstamos | B17: 250 | C17: 250 | D17: 250 | E17: 250 | F17: 250 | G17: 250 | H17: 250 | I17: 250 | J17: 250 | K17: 250 | L17: 250 | M17: 250 | N17: =SUM(B17:M17) -> 3000
A18: =Categorias!$B$18 -> Otros gastos | B18: 50 | C18: 50 | D18: 50 | E18: 50 | F18: 50 | G18: 50 | H18: 50 | I18: 50 | J18: 50 | K18: 50 | L18: 50 | M18: 50 | N18: =SUM(B18:M18) -> 600
A19: TOTAL | B19: =SUM(B5:B18) -> 7230 | C19: =SUM(C5:C18) -> 7230 | D19: =SUM(D5:D18) -> 7230 | E19: =SUM(E5:E18) -> 7230 | F19: =SUM(F5:F18) -> 7230 | G19: =SUM(G5:G18) -> 7230 | H19: =SUM(H5:H18) -> 7230 | I19: =SUM(I5:I18) -> 7230 | ... N19: =SUM(N5:N18) -> 86760

Sheet Real
A2: GASTOS E INGRESOS REALES (por categoría y mes)
A4: Categoría | B4: Ene | C4: Feb | D4: Mar | E4: Abr | F4: May | G4: Jun | H4: Jul | I4: Ago | J4: Sep | K4: Oct | L4: Nov | M4: Dic | N4: Total anual
A5: =Categorias!$B$5 -> Salario | B5: 4500 | C5: 4500 | D5: 4600 | N5: =SUM(B5:M5) -> 13600
A6: =Categorias!$B$6 -> Freelance / Ingresos extra | B6: 350 | C6: 0 | D6: 0 | N6: =SUM(B6:M6) -> 350
A7: =Categorias!$B$7 -> Otros ingresos | B7: 0 | C7: 150 | D7: 0 | N7: =SUM(B7:M7) -> 150
A8: =Categorias!$B$8 -> Vivienda (alquiler/hipoteca) | B8: 1200 | C8: 1200 | D8: 1200 | N8: =SUM(B8:M8) -> 3600
A9: =Categorias!$B$9 -> Alimentación | B9: 180 | C9: 210 | D9: 195 | N9: =SUM(B9:M9) -> 585
A10: =Categorias!$B$10 -> Transporte | B10: 60 | C10: 120 | D10: 0 | N10: =SUM(B10:M10) -> 180
A11: =Categorias!$B$11 -> Servicios (luz, agua, internet) | B11: 75 | C11: 0 | D11: 0 | N11: =SUM(B11:M11) -> 75
A12: =Categorias!$B$12 -> Salud | B12: 90 | C12: 0 | D12: 0 | N12: =SUM(B12:M12) -> 90
A13: =Categorias!$B$13 -> Educación | B13: 0 | C13: 80 | D13: 0 | N13: =SUM(B13:M13) -> 80
A14: =Categorias!$B$14 -> Entretenimiento | B14: 45 | C14: 25 | D14: 0 | N14: =SUM(B14:M14) -> 70
A15: =Categorias!$B$15 -> Ropa y cuidado personal | B15: 0 | C15: 0 | D15: 0 | N15: =SUM(B15:M15) -> 0
A16: =Categorias!$B$16 -> Ahorro e inversión | B16: 300 | C16: 0 | D16: 0 | N16: =SUM(B16:M16) -> 300
A17: =Categorias!$B$17 -> Deudas y préstamos | B17: 0 | C17: 0 | D17: 250 | N17: =SUM(B17:M17) -> 250
A18: =Categorias!$B$18 -> Otros gastos | B18: 0 | C18: 0 | D18: 0 | N18: =SUM(B18:M18) -> 0
A19: TOTAL | B19: =SUM(B5:B18) -> 6800 | C19: =SUM(C5:C18) -> 6285 | D19: =SUM(D5:D18) -> 6245 | E19: =SUM(E5:E18) -> 0 | F19: =SUM(F5:F18) -> 0 | G19: =SUM(G5:G18) -> 0 | H19: =SUM(H5:H18) -> 0 | I19: =SUM(I5:I18) -> 0 | ... N19: =SUM(N5:N18) -> 19330

Sheet Resumen
B2: RESUMEN DINÁMICO (se actualiza solo)
B3: =" Mes analizado: " & Configuracion!$C$10 & " | Moneda: " & Configuracion!$C$8 -> Mes analizado: Enero | Moneda: Local
B5: PRESUPUESTADO VS. REAL POR CATEGORÍA (mes seleccionado)
B6: Categoría | C6: Presupuestado | D6: Real | E6: Diferencia | F6: % usado
B7: =Categorias!$B$5 -> Salario | C7: =INDEX(Presupuesto!$B$5:$M$5,Configuracion!$C$14)*Configuracion!$C$12 -> 4500 | D7: =INDEX(Real!$B$5:$M$5,Configuracion!$C$14)*Configuracion!$C$12 -> 4500 | E7: =C7-D7 -> 0 | F7: =IF(C7=0,0,D7/C7) -> 1
B8: =Categorias!$B$6 -> Freelance / Ingresos extra | C8: =INDEX(Presupuesto!$B$6:$M$6,Configuracion!$C$14)*Configuracion!$C$12 -> 300 | D8: =INDEX(Real!$B$6:$M$6,Configuracion!$C$14)*Configuracion!$C$12 -> 350 | E8: =C8-D8 -> -50 | F8: =IF(C8=0,0,D8/C8) -> 1.1666667
B9: =Categorias!$B$7 -> Otros ingresos | C9: =INDEX(Presupuesto!$B$7:$M$7,Configuracion!$C$14)*Configuracion!$C$12 -> 0 | D9: =INDEX(Real!$B$7:$M$7,Configuracion!$C$14)*Configuracion!$C$12 -> 0 | E9: =C9-D9 -> 0 | F9: =IF(C9=0,0,D9/C9) -> 0
B10: =Categorias!$B$8 -> Vivienda (alquiler/hipoteca) | C10: =INDEX(Presupuesto!$B$8:$M$8,Configuracion!$C$14)*Configuracion!$C$12 -> 1200 | D10: =INDEX(Real!$B$8:$M$8,Configuracion!$C$14)*Configuracion!$C$12 -> 1200 | E10: =C10-D10 -> 0 | F10: =IF(C10=0,0,D10/C10) -> 1
B11: =Categorias!$B$9 -> Alimentación | C11: =INDEX(Presupuesto!$B$9:$M$9,Configuracion!$C$14)*Configuracion!$C$12 -> 200 | D11: =INDEX(Real!$B$9:$M$9,Configuracion!$C$14)*Configuracion!$C$12 -> 180 | E11: =C11-D11 -> 20 | F11: =IF(C11=0,0,D11/C11) -> 0.9
B12: =Categorias!$B$10 -> Transporte | C12: =INDEX(Presupuesto!$B$10:$M$10,Configuracion!$C$14)*Configuracion!$C$12 -> 100 | D12: =INDEX(Real!$B$10:$M$10,Configuracion!$C$14)*Configuracion!$C$12 -> 60 | E12: =C12-D12 -> 40 | F12: =IF(C12=0,0,D12/C12) -> 0.6
B13: =Categorias!$B$11 -> Servicios (luz, agua, internet) | C13: =INDEX(Presupuesto!$B$11:$M$11,Configuracion!$C$14)*Configuracion!$C$12 -> 80 | D13: =INDEX(Real!$B$11:$M$11,Configuracion!$C$14)*Configuracion!$C$12 -> 75 | E13: =C13-D13 -> 5 | F13: =IF(C13=0,0,D13/C13) -> 0.9375
B14: =Categorias!$B$12 -> Salud | C14: =INDEX(Presupuesto!$B$12:$M$12,Configuracion!$C$14)*Configuracion!$C$12 -> 60 | D14: =INDEX(Real!$B$12:$M$12,Configuracion!$C$14)*Configuracion!$C$12 -> 90 | E14: =C14-D14 -> -30 | F14: =IF(C14=0,0,D14/C14) -> 1.5
B15: =Categorias!$B$13 -> Educación | C15: =INDEX(Presupuesto!$B$13:$M$13,Configuracion!$C$14)*Configuracion!$C$12 -> 80 | D15: =INDEX(Real!$B$13:$M$13,Configuracion!$C$14)*Configuracion!$C$12 -> 0 | E15: =C15-D15 -> 80 | F15: =IF(C15=0,0,D15/C15) -> 0
B16: =Categorias!$B$14 -> Entretenimiento | C16: =INDEX(Presupuesto!$B$14:$M$14,Configuracion!$C$14)*Configuracion!$C$12 -> 60 | D16: =INDEX(Real!$B$14:$M$14,Configuracion!$C$14)*Configuracion!$C$12 -> 45 | E16: =C16-D16 -> 15 | F16: =IF(C16=0,0,D16/C16) -> 0.75
B17: =Categorias!$B$15 -> Ropa y cuidado personal | C17: =INDEX(Presupuesto!$B$15:$M$15,Configuracion!$C$14)*Configuracion!$C$12 -> 50 | D17: =INDEX(Real!$B$15:$M$15,Configuracion!$C$14)*Configuracion!$C$12 -> 0 | E17: =C17-D17 -> 50 | F17: =IF(C17=0,0,D17/C17) -> 0
B18: =Categorias!$B$16 -> Ahorro e inversión | C18: =INDEX(Presupuesto!$B$16:$M$16,Configuracion!$C$14)*Configuracion!$C$12 -> 300 | D18: =INDEX(Real!$B$16:$M$16,Configuracion!$C$14)*Configuracion!$C$12 -> 300 | E18: =C18-D18 -> 0 | F18: =IF(C18=0,0,D18/C18) -> 1
B19: =Categorias!$B$17 -> Deudas y préstamos | C19: =INDEX(Presupuesto!$B$17:$M$17,Configuracion!$C$14)*Configuracion!$C$12 -> 250 | D19: =INDEX(Real!$B$17:$M$17,Configuracion!$C$14)*Configuracion!$C$12 -> 0 | E19: =C19-D19 -> 250 | F19: =IF(C19=0,0,D19/C19) -> 0
B20: =Categorias!$B$18 -> Otros gastos | C20: =INDEX(Presupuesto!$B$18:$M$18,Configuracion!$C$14)*Configuracion!$C$12 -> 50 | D20: =INDEX(Real!$B$18:$M$18,Configuracion!$C$14)*Configuracion!$C$12 -> 0 | E20: =C20-D20 -> 50 | F20: =IF(C20=0,0,D20/C20) -> 0
B21: TOTAL INGRESOS | C21: =SUM(C7:C9) -> 4800 | D21: =SUM(D7:D9) -> 4850 | E21: =SUM(E7:E9) -> -50 | F21: =IF(C21=0,0,D21/C21) -> 1.0104167
B22: TOTAL GASTOS | C22: =SUM(C10:C20) -> 2430 | D22: =SUM(D10:D20) -> 1950 | E22: =SUM(E10:E20) -> 480 | F22: =IF(C22=0,0,D22/C22) -> 0.80246914
B23: BALANCE (Ingresos - Gastos) | C23: =C21-C22 -> 2370 | D23: =D21-D22 -> 2900 | E23: =E21-E22 -> -530
B26: EVOLUCIÓN MENSUAL (todo el año)
B27: Mes | C27: Presupuestado | D27: Real | E27: Diferencia
B28: Enero | C28: =Presupuesto!B$19*Configuracion!$C$12 -> 7230 | D28: =Real!B$19*Configuracion!$C$12 -> 6800 | E28: =C28-D28 -> 430
B29: Febrero | C29: =Presupuesto!C$19*Configuracion!$C$12 -> 7230 | D29: =Real!C$19*Configuracion!$C$12 -> 6285 | E29: =C29-D29 -> 945
B30: Marzo | C30: =Presupuesto!D$19*Configuracion!$C$12 -> 7230 | D30: =Real!D$19*Configuracion!$C$12 -> 6245 | E30: =C30-D30 -> 985
B31: Abril | C31: =Presupuesto!E$19*Configuracion!$C$12 -> 7230 | D31: =Real!E$19*Configuracion!$C$12 -> 0 | E31: =C31-D31 -> 7230
B32: Mayo | C32: =Presupuesto!F$19*Configuracion!$C$12 -> 7230 | D32: =Real!F$19*Configuracion!$C$12 -> 0 | E32: =C32-D32 -> 7230
B33: Junio | C33: =Presupuesto!G$19*Configuracion!$C$12 -> 7230 | D33: =Real!G$19*Configuracion!$C$12 -> 0 | E33: =C33-D33 -> 7230
B34: Julio | C34: =Presupuesto!H$19*Configuracion!$C$12 -> 7230 | D34: =Real!H$19*Configuracion!$C$12 -> 0 | E34: =C34-D34 -> 7230
B35: Agosto | C35: =Presupuesto!I$19*Configuracion!$C$12 -> 7230 | D35: =Real!I$19*Configuracion!$C$12 -> 0 | E35: =C35-D35 -> 7230
B36: Septiembre | C36: =Presupuesto!J$19*Configuracion!$C$12 -> 7230 | D36: =Real!J$19*Configuracion!$C$12 -> 0 | E36: =C36-D36 -> 7230
B37: Octubre | C37: =Presupuesto!K$19*Configuracion!$C$12 -> 7230 | D37: =Real!K$19*Configuracion!$C$12 -> 0 | E37: =C37-D37 -> 7230
B38: Noviembre | C38: =Presupuesto!L$19*Configuracion!$C$12 -> 7230 | D38: =Real!L$19*Configuracion!$C$12 -> 0 | E38: =C38-D38 -> 7230
B39: Diciembre | C39: =Presupuesto!M$19*Configuracion!$C$12 -> 7230 | D39: =Real!M$19*Configuracion!$C$12 -> 0 | E39: =C39-D39 -> 7230

Sheet Dashboard
B2: DASHBOARD · PRESUPUESTO MENSUAL
B3: =" Mes: " & Configuracion!$C$10 & " | Moneda: " & Configuracion!$C$8 & " | Año: " & Configuracion!$C$9 -> Mes: Enero | Moneda: Local | Año: 2026
B5: INGRESO REAL (MES) | D5: GASTO PRESUPUESTADO (MES) | F5: GASTO REAL (MES) | H5: % DE GASTOS USADO
B6: =Configuracion!$C$13&" "&TEXT(Resumen!D21,"#,##0.00") -> S/ 4,850.00 | D6: =Configuracion!$C$13&" "&TEXT(Resumen!C22,"#,##0.00") -> S/ 2,430.00 | F6: =Configuracion!$C$13&" "&TEXT(Resumen!D22,"#,##0.00") -> S/ 1,950.00 | H6: =IF(Resumen!C22=0,"0.0%",TEXT(Resumen!D22/Resumen!C22,"0.0%")) -> 80.2%
