Workbook

Sheet Portada
B2: LÍNEA DE PRODUCTOS DIGITALES · PLANTILLAS EXCEL
B4: CONTROL DE DEUDAS
B7: Registra todas tus deudas, controla tus pagos (capital e interés) y descubre qué deuda conviene pagar primero — con panel de control, gráficos automáticos y selector de moneda (local / USD).
B10: QUÉ INCLUYE ESTA PLANTILLA
B11: ✔ Dashboard con indicadores clave (KPIs) y gráficos automáticos
B12: ✔ Fórmulas automáticas: nada que calcular a mano
B13: ✔ Gráficos: pastel, barras y evolución de la deuda total
B14: ✔ Resumen dinámico tipo tabla dinámica por deuda
B15: ✔ Estrategias sugeridas de pago: bola de nieve y avalancha
B16: ✔ Listas desplegables y validación de datos en cada registro
B17: ✔ Selector de moneda: local o USD, con tipo de cambio editable
B18: ✔ Hoja de instrucciones paso a paso
... B24: © Tu Marca de Plantillas · www.tumarca.com

Sheet Instrucciones
B2: CÓMO USAR ESTA PLANTILLA
B4: 1. Configuración
B5: Define el símbolo de tu moneda local, el tipo de cambio y si la plantilla se muestra en moneda LOCAL o USD.
B7: 2. Deudas
B8: En la hoja 'Deudas' registra cada deuda: nombre, tipo, saldo inicial, tasa de interés anual y pago mínimo mensual. El saldo actual y el % pagado se calculan solos. Hay espacio para hasta 10 deudas; si necesitas más, copia el formato de una fila hacia abajo en Deudas y Resumen.
B10: 3. Pagos
B11: Cada vez que pagues una deuda, agrégalo en la hoja 'Pagos': fecha, deuda (lista desplegable), monto total pagado e interés de ese pago. El capital amortizado se calcula solo.
B13: 4. Resumen automático
B14: La hoja 'Resumen' agrupa automáticamente tus pagos por deuda y te sugiere un orden de pago con dos estrategias: 'Bola de nieve' (pagar primero la deuda más pequeña) y 'Avalancha' (pagar primero la de mayor interés).
B16: 5. Dashboard
B17: La hoja 'Dashboard' muestra tu deuda total, lo pagado, el interés acumulado y la evolución de tu deuda total mes a mes, con gráficos que se actualizan solos.
B19: 6. Cambiar de moneda
... B25: Soporte y otras plantillas de esta línea de productos: www.tumarca.com

Sheet Configuracion
B2: CONFIGURACIÓN Y MONEDA
B4: Parámetro | C4: Valor | D4: Notas
B5: Nombre de moneda local | C5: Soles (PEN) | D5: Solo referencia. Escribe el nombre de tu moneda.
B6: Símbolo de moneda local | C6: S/ | D6: Símbolo que se usará en el Dashboard cuando la vista esté en LOCAL.
B7: Tipo de cambio (1 USD =) | C7: 3.75 | D7: Cuántas unidades de tu moneda local equivalen a 1 USD.
B8: Moneda de visualización | C8: Local | D8: Elige LOCAL o USD. Afecta Resumen y Dashboard.
B9: Año de análisis | C9: 2026 | D9: Año que se usa para agrupar la evolución mensual.
B10: Valores calculados (no editar)
B11: Factor de conversión aplicado | C11: =IF(C8="USD",1/C7,1) -> 1 | D11: Vale 1 si vista LOCAL; vale 1/Tipo de cambio si vista USD.
B12: Símbolo de moneda actual | C12: =IF(C8="USD","US$",C6) -> S/ | D12: Símbolo que verás en el Dashboard según la moneda elegida.
B14: Cambia 'Moneda de visualización' entre Local y USD para recalcular automáticamente toda la plantilla.

Sheet Deudas
A2: REGISTRO DE DEUDAS
A3: Completa las columnas A a E para cada deuda. Las columnas F a J se calculan automáticamente.
A4: Deuda | B4: Tipo | C4: Saldo inicial | D4: Tasa interés anual | E4: Pago mínimo mensual | F4: Total pagado | G4: Interés pagado | H4: Capital pagado | I4: Saldo actual | J4: % pagado
A5: Tarjeta Visa | B5: Tarjeta de crédito | C5: 3000 | D5: 0.28 | E5: 150 | F5: =SUMIFS(Pagos!$C$5:$C$204,Pagos!$B$5:$B$204,$A5) -> 800 | G5: =SUMIFS(Pagos!$D$5:$D$204,Pagos!$B$5:$B$204,$A5) -> 183 | H5: =SUMIFS(Pagos!$E$5:$E$204,Pagos!$B$5:$B$204,$A5) -> 617 | I5: =IF($A5="","",$C5-$H5) -> 2383 | J5: =IF(OR($A5="",$C5=0),0,$H5/$C5) -> 0.20566667
A6: Tarjeta Mastercard | B6: Tarjeta de crédito | C6: 1500 | D6: 0.32 | E6: 80 | F6: =SUMIFS(Pagos!$C$5:$C$204,Pagos!$B$5:$B$204,$A6) -> 360 | G6: =SUMIFS(Pagos!$D$5:$D$204,Pagos!$B$5:$B$204,$A6) -> 106 | H6: =SUMIFS(Pagos!$E$5:$E$204,Pagos!$B$5:$B$204,$A6) -> 254 | I6: =IF($A6="","",$C6-$H6) -> 1246 | J6: =IF(OR($A6="",$C6=0),0,$H6/$C6) -> 0.16933333
A7: Préstamo auto | B7: Préstamo vehicular | C7: 8000 | D7: 0.12 | E7: 320 | F7: =SUMIFS(Pagos!$C$5:$C$204,Pagos!$B$5:$B$204,$A7) -> 960 | G7: =SUMIFS(Pagos!$D$5:$D$204,Pagos!$B$5:$B$204,$A7) -> 223 | H7: =SUMIFS(Pagos!$E$5:$E$204,Pagos!$B$5:$B$204,$A7) -> 737 | I7: =IF($A7="","",$C7-$H7) -> 7263 | J7: =IF(OR($A7="",$C7=0),0,$H7/$C7) -> 0.092125
A8: Préstamo personal | B8: Préstamo personal | C8: 2000 | D8: 0.18 | E8: 150 | F8: =SUMIFS(Pagos!$C$5:$C$204,Pagos!$B$5:$B$204,$A8) -> 450 | G8: =SUMIFS(Pagos!$D$5:$D$204,Pagos!$B$5:$B$204,$A8) -> 78 | H8: =SUMIFS(Pagos!$E$5:$E$204,Pagos!$B$5:$B$204,$A8) -> 372 | I8: =IF($A8="","",$C8-$H8) -> 1628 | J8: =IF(OR($A8="",$C8=0),0,$H8/$C8) -> 0.186
A9: Hipoteca | B9: Hipoteca | C9: 45000 | D9: 0.08 | E9: 450 | F9: =SUMIFS(Pagos!$C$5:$C$204,Pagos!$B$5:$B$204,$A9) -> 1350 | G9: =SUMIFS(Pagos!$D$5:$D$204,Pagos!$B$5:$B$204,$A9) -> 876 | H9: =SUMIFS(Pagos!$E$5:$E$204,Pagos!$B$5:$B$204,$A9) -> 474 | I9: =IF($A9="","",$C9-$H9) -> 44526 | J9: =IF(OR($A9="",$C9=0),0,$H9/$C9) -> 0.010533333
F10: =SUMIFS(Pagos!$C$5:$C$204,Pagos!$B$5:$B$204,$A10) -> 0 | G10: =SUMIFS(Pagos!$D$5:$D$204,Pagos!$B$5:$B$204,$A10) -> 0 | H10: =SUMIFS(Pagos!$E$5:$E$204,Pagos!$B$5:$B$204,$A10) -> 0 | I10: =IF($A10="","",$C10-$H10) | J10: =IF(OR($A10="",$C10=0),0,$H10/$C10) -> 0
F11: =SUMIFS(Pagos!$C$5:$C$204,Pagos!$B$5:$B$204,$A11) -> 0 | G11: =SUMIFS(Pagos!$D$5:$D$204,Pagos!$B$5:$B$204,$A11) -> 0 | H11: =SUMIFS(Pagos!$E$5:$E$204,Pagos!$B$5:$B$204,$A11) -> 0 | I11: =IF($A11="","",$C11-$H11) | J11: =IF(OR($A11="",$C11=0),0,$H11/$C11) -> 0
F12: =SUMIFS(Pagos!$C$5:$C$204,Pagos!$B$5:$B$204,$A12) -> 0 | G12: =SUMIFS(Pagos!$D$5:$D$204,Pagos!$B$5:$B$204,$A12) -> 0 | H12: =SUMIFS(Pagos!$E$5:$E$204,Pagos!$B$5:$B$204,$A12) -> 0 | I12: =IF($A12="","",$C12-$H12) | J12: =IF(OR($A12="",$C12=0),0,$H12/$C12) -> 0
F13: =SUMIFS(Pagos!$C$5:$C$204,Pagos!$B$5:$B$204,$A13) -> 0 | G13: =SUMIFS(Pagos!$D$5:$D$204,Pagos!$B$5:$B$204,$A13) -> 0 | H13: =SUMIFS(Pagos!$E$5:$E$204,Pagos!$B$5:$B$204,$A13) -> 0 | I13: =IF($A13="","",$C13-$H13) | J13: =IF(OR($A13="",$C13=0),0,$H13/$C13) -> 0
F14: =SUMIFS(Pagos!$C$5:$C$204,Pagos!$B$5:$B$204,$A14) -> 0 | G14: =SUMIFS(Pagos!$D$5:$D$204,Pagos!$B$5:$B$204,$A14) -> 0 | H14: =SUMIFS(Pagos!$E$5:$E$204,Pagos!$B$5:$B$204,$A14) -> 0 | I14: =IF($A14="","",$C14-$H14) | J14: =IF(OR($A14="",$C14=0),0,$H14/$C14) -> 0
A15: TOTAL | C15: =SUM(C5:C14) -> 59500 | E15: =SUM(E5:E14) -> 1150 | F15: =SUM(F5:F14) -> 3920 | G15: =SUM(G5:G14) -> 1466 | H15: =SUM(H5:H14) -> 2454 | I15: =SUM(I5:I14) -> 57046 | J15: =IF(C15=0,0,H15/C15) -> 0.041243697

Sheet Pagos
A2: REGISTRO DE PAGOS
A3: Completa las columnas A a D para cada pago. La columna E (capital) se calcula automáticamente.
A4: Fecha | B4: Deuda | C4: Monto pagado | D4: Interés del pago | E4: Capital amortizado
A5: 46027 | B5: Tarjeta Visa | C5: 250 | D5: 65 | E5: =IF(C5="","",C5-D5) -> 185
A6: 46030 | B6: Tarjeta Mastercard | C6: 120 | D6: 38 | E6: =IF(C6="","",C6-D6) -> 82
A7: 46032 | B7: Préstamo auto | C7: 320 | D7: 78 | E7: =IF(C7="","",C7-D7) -> 242
A8: 46034 | B8: Préstamo personal | C8: 150 | D8: 28 | E8: =IF(C8="","",C8-D8) -> 122
A9: 46037 | B9: Hipoteca | C9: 450 | D9: 295 | E9: =IF(C9="","",C9-D9) -> 155
A10: 46058 | B10: Tarjeta Visa | C10: 250 | D10: 60 | E10: =IF(C10="","",C10-D10) -> 190
A11: 46061 | B11: Tarjeta Mastercard | C11: 120 | D11: 35 | E11: =IF(C11="","",C11-D11) -> 85
A12: 46063 | B12: Préstamo auto | C12: 320 | D12: 74 | E12: =IF(C12="","",C12-D12) -> 246
A13: 46065 | B13: Préstamo personal | C13: 150 | D13: 26 | E13: =IF(C13="","",C13-D13) -> 124
A14: 46068 | B14: Hipoteca | C14: 450 | D14: 292 | E14: =IF(C14="","",C14-D14) -> 158
A15: 46086 | B15: Tarjeta Visa | C15: 300 | D15: 58 | E15: =IF(C15="","",C15-D15) -> 242
A16: 46089 | B16: Tarjeta Mastercard | C16: 120 | D16: 33 | E16: =IF(C16="","",C16-D16) -> 87
... A19: 46096 | B19: Hipoteca | C19: 450 | D19: 289 | E19: =IF(C19="","",C19-D19) -> 161
E20: =IF(C20="","",C20-D20)
E21: =IF(C21="","",C21-D21)
E22: =IF(C22="","",C22-D22)
E23: =IF(C23="","",C23-D23)
E24: =IF(C24="","",C24-D24)
E25: =IF(C25="","",C25-D25)
E26: =IF(C26="","",C26-D26)
E27: =IF(C27="","",C27-D27)
E28: =IF(C28="","",C28-D28)
E29: =IF(C29="","",C29-D29)
E30: =IF(C30="","",C30-D30)
E31: =IF(C31="","",C31-D31)
... E204: =IF(C204="","",C204-D204)

Sheet Resumen
B2: RESUMEN DINÁMICO (se actualiza solo)
B3: =" Moneda: " & Configuracion!$C$8 -> Moneda: Local
B5: DEUDAS Y ESTRATEGIA DE PAGO SUGERIDA
B6: Deuda | C6: Saldo inicial | D6: Saldo actual | E6: % pagado | F6: Tasa interés | G6: Bola de nieve | H6: Avalancha
B7: =Deudas!$A$5 -> Tarjeta Visa | C7: =Deudas!$C$5*Configuracion!$C$11 -> 3000 | D7: =IF(Deudas!$A$5="",0,Deudas!$I$5*Configuracion!$C$11) -> 2383 | E7: =Deudas!$J$5 -> 0.20566667 | F7: =Deudas!$D$5 -> 0.28 | G7: =IF(Deudas!$A$5="","",IF(Deudas!$I$5<=0,"Pagada",RANK(Deudas!$I$5,Deudas!$I$5:$I$14,1))) -> 3 | H7: =IF(Deudas!$A$5="","",IF(Deudas!$I$5<=0,"Pagada",RANK(Deudas!$D$5,Deudas!$D$5:$D$14,0))) -> 2
B8: =Deudas!$A$6 -> Tarjeta Mastercard | C8: =Deudas!$C$6*Configuracion!$C$11 -> 1500 | D8: =IF(Deudas!$A$6="",0,Deudas!$I$6*Configuracion!$C$11) -> 1246 | E8: =Deudas!$J$6 -> 0.16933333 | F8: =Deudas!$D$6 -> 0.32 | G8: =IF(Deudas!$A$6="","",IF(Deudas!$I$6<=0,"Pagada",RANK(Deudas!$I$6,Deudas!$I$5:$I$14,1))) -> 1 | H8: =IF(Deudas!$A$6="","",IF(Deudas!$I$6<=0,"Pagada",RANK(Deudas!$D$6,Deudas!$D$5:$D$14,0))) -> 1
B9: =Deudas!$A$7 -> Préstamo auto | C9: =Deudas!$C$7*Configuracion!$C$11 -> 8000 | D9: =IF(Deudas!$A$7="",0,Deudas!$I$7*Configuracion!$C$11) -> 7263 | E9: =Deudas!$J$7 -> 0.092125 | F9: =Deudas!$D$7 -> 0.12 | G9: =IF(Deudas!$A$7="","",IF(Deudas!$I$7<=0,"Pagada",RANK(Deudas!$I$7,Deudas!$I$5:$I$14,1))) -> 4 | H9: =IF(Deudas!$A$7="","",IF(Deudas!$I$7<=0,"Pagada",RANK(Deudas!$D$7,Deudas!$D$5:$D$14,0))) -> 4
B10: =Deudas!$A$8 -> Préstamo personal | C10: =Deudas!$C$8*Configuracion!$C$11 -> 2000 | D10: =IF(Deudas!$A$8="",0,Deudas!$I$8*Configuracion!$C$11) -> 1628 | E10: =Deudas!$J$8 -> 0.186 | F10: =Deudas!$D$8 -> 0.18 | G10: =IF(Deudas!$A$8="","",IF(Deudas!$I$8<=0,"Pagada",RANK(Deudas!$I$8,Deudas!$I$5:$I$14,1))) -> 2 | H10: =IF(Deudas!$A$8="","",IF(Deudas!$I$8<=0,"Pagada",RANK(Deudas!$D$8,Deudas!$D$5:$D$14,0))) -> 3
B11: =Deudas!$A$9 -> Hipoteca | C11: =Deudas!$C$9*Configuracion!$C$11 -> 45000 | D11: =IF(Deudas!$A$9="",0,Deudas!$I$9*Configuracion!$C$11) -> 44526 | E11: =Deudas!$J$9 -> 0.010533333 | F11: =Deudas!$D$9 -> 0.08 | G11: =IF(Deudas!$A$9="","",IF(Deudas!$I$9<=0,"Pagada",RANK(Deudas!$I$9,Deudas!$I$5:$I$14,1))) -> 5 | H11: =IF(Deudas!$A$9="","",IF(Deudas!$I$9<=0,"Pagada",RANK(Deudas!$D$9,Deudas!$D$5:$D$14,0))) -> 5
B12: =Deudas!$A$10 -> 0 | C12: =Deudas!$C$10*Configuracion!$C$11 -> 0 | D12: =IF(Deudas!$A$10="",0,Deudas!$I$10*Configuracion!$C$11) -> 0 | E12: =Deudas!$J$10 -> 0 | F12: =Deudas!$D$10 -> 0 | G12: =IF(Deudas!$A$10="","",IF(Deudas!$I$10<=0,"Pagada",RANK(Deudas!$I$10,Deudas!$I$5:$I$14,1))) | H12: =IF(Deudas!$A$10="","",IF(Deudas!$I$10<=0,"Pagada",RANK(Deudas!$D$10,Deudas!$D$5:$D$14,0)))
B13: =Deudas!$A$11 -> 0 | C13: =Deudas!$C$11*Configuracion!$C$11 -> 0 | D13: =IF(Deudas!$A$11="",0,Deudas!$I$11*Configuracion!$C$11) -> 0 | E13: =Deudas!$J$11 -> 0 | F13: =Deudas!$D$11 -> 0 | G13: =IF(Deudas!$A$11="","",IF(Deudas!$I$11<=0,"Pagada",RANK(Deudas!$I$11,Deudas!$I$5:$I$14,1))) | H13: =IF(Deudas!$A$11="","",IF(Deudas!$I$11<=0,"Pagada",RANK(Deudas!$D$11,Deudas!$D$5:$D$14,0)))
B14: =Deudas!$A$12 -> 0 | C14: =Deudas!$C$12*Configuracion!$C$11 -> 0 | D14: =IF(Deudas!$A$12="",0,Deudas!$I$12*Configuracion!$C$11) -> 0 | E14: =Deudas!$J$12 -> 0 | F14: =Deudas!$D$12 -> 0 | G14: =IF(Deudas!$A$12="","",IF(Deudas!$I$12<=0,"Pagada",RANK(Deudas!$I$12,Deudas!$I$5:$I$14,1))) | H14: =IF(Deudas!$A$12="","",IF(Deudas!$I$12<=0,"Pagada",RANK(Deudas!$D$12,Deudas!$D$5:$D$14,0)))
B15: =Deudas!$A$13 -> 0 | C15: =Deudas!$C$13*Configuracion!$C$11 -> 0 | D15: =IF(Deudas!$A$13="",0,Deudas!$I$13*Configuracion!$C$11) -> 0 | E15: =Deudas!$J$13 -> 0 | F15: =Deudas!$D$13 -> 0 | G15: =IF(Deudas!$A$13="","",IF(Deudas!$I$13<=0,"Pagada",RANK(Deudas!$I$13,Deudas!$I$5:$I$14,1))) | H15: =IF(Deudas!$A$13="","",IF(Deudas!$I$13<=0,"Pagada",RANK(Deudas!$D$13,Deudas!$D$5:$D$14,0)))
B16: =Deudas!$A$14 -> 0 | C16: =Deudas!$C$14*Configuracion!$C$11 -> 0 | D16: =IF(Deudas!$A$14="",0,Deudas!$I$14*Configuracion!$C$11) -> 0 | E16: =Deudas!$J$14 -> 0 | F16: =Deudas!$D$14 -> 0 | G16: =IF(Deudas!$A$14="","",IF(Deudas!$I$14<=0,"Pagada",RANK(Deudas!$I$14,Deudas!$I$5:$I$14,1))) | H16: =IF(Deudas!$A$14="","",IF(Deudas!$I$14<=0,"Pagada",RANK(Deudas!$D$14,Deudas!$D$5:$D$14,0)))
B17: TOTAL | C17: =SUM(C7:C16) -> 59500 | D17: =SUM(D7:D16) -> 57046 | E17: =IF(C17=0,0,1-D17/C17) -> 0.041243697
B20: EVOLUCIÓN DE LA DEUDA TOTAL (saldo acumulado al cierre de cada mes)
B21: Mes | C21: Saldo total
B22: Enero | C22: =(SUM(Deudas!$C$5:$C$14)-SUMIFS(Pagos!$E$5:$E$204,Pagos!$A$5:$A$204,"<="&EOMONTH(DATE(Configuracion!$C$9,1,1),0)))*Configuracion!$C$11 -> 58714
B23: Febrero | C23: =(SUM(Deudas!$C$5:$C$14)-SUMIFS(Pagos!$E$5:$E$204,Pagos!$A$5:$A$204,"<="&EOMONTH(DATE(Configuracion!$C$9,2,1),0)))*Configuracion!$C$11 -> 57911
B24: Marzo | C24: =(SUM(Deudas!$C$5:$C$14)-SUMIFS(Pagos!$E$5:$E$204,Pagos!$A$5:$A$204,"<="&EOMONTH(DATE(Configuracion!$C$9,3,1),0)))*Configuracion!$C$11 -> 57046
B25: Abril | C25: =(SUM(Deudas!$C$5:$C$14)-SUMIFS(Pagos!$E$5:$E$204,Pagos!$A$5:$A$204,"<="&EOMONTH(DATE(Configuracion!$C$9,4,1),0)))*Configuracion!$C$11 -> 57046
B26: Mayo | C26: =(SUM(Deudas!$C$5:$C$14)-SUMIFS(Pagos!$E$5:$E$204,Pagos!$A$5:$A$204,"<="&EOMONTH(DATE(Configuracion!$C$9,5,1),0)))*Configuracion!$C$11 -> 57046
B27: Junio | C27: =(SUM(Deudas!$C$5:$C$14)-SUMIFS(Pagos!$E$5:$E$204,Pagos!$A$5:$A$204,"<="&EOMONTH(DATE(Configuracion!$C$9,6,1),0)))*Configuracion!$C$11 -> 57046
B28: Julio | C28: =(SUM(Deudas!$C$5:$C$14)-SUMIFS(Pagos!$E$5:$E$204,Pagos!$A$5:$A$204,"<="&EOMONTH(DATE(Configuracion!$C$9,7,1),0)))*Configuracion!$C$11 -> 57046
B29: Agosto | C29: =(SUM(Deudas!$C$5:$C$14)-SUMIFS(Pagos!$E$5:$E$204,Pagos!$A$5:$A$204,"<="&EOMONTH(DATE(Configuracion!$C$9,8,1),0)))*Configuracion!$C$11 -> 57046
B30: Septiembre | C30: =(SUM(Deudas!$C$5:$C$14)-SUMIFS(Pagos!$E$5:$E$204,Pagos!$A$5:$A$204,"<="&EOMONTH(DATE(Configuracion!$C$9,9,1),0)))*Configuracion!$C$11 -> 57046
B31: Octubre | C31: =(SUM(Deudas!$C$5:$C$14)-SUMIFS(Pagos!$E$5:$E$204,Pagos!$A$5:$A$204,"<="&EOMONTH(DATE(Configuracion!$C$9,10,1),0)))*Configuracion!$C$11 -> 57046
B32: Noviembre | C32: =(SUM(Deudas!$C$5:$C$14)-SUMIFS(Pagos!$E$5:$E$204,Pagos!$A$5:$A$204,"<="&EOMONTH(DATE(Configuracion!$C$9,11,1),0)))*Configuracion!$C$11 -> 57046
B33: Diciembre | C33: =(SUM(Deudas!$C$5:$C$14)-SUMIFS(Pagos!$E$5:$E$204,Pagos!$A$5:$A$204,"<="&EOMONTH(DATE(Configuracion!$C$9,12,1),0)))*Configuracion!$C$11 -> 57046

Sheet Dashboard
B2: DASHBOARD · CONTROL DE DEUDAS
B3: =" Moneda de visualización: " & Configuracion!$C$8 -> Moneda de visualización: Local
B5: DEUDA INICIAL TOTAL | D5: SALDO ACTUAL TOTAL | F5: TOTAL PAGADO | H5: % DEUDA PAGADA
B6: =Configuracion!$C$12&" "&TEXT(Resumen!C17,"#,##0.00") -> S/ 59,500.00 | D6: =Configuracion!$C$12&" "&TEXT(Resumen!D17,"#,##0.00") -> S/ 57,046.00 | F6: =Configuracion!$C$12&" "&TEXT(Resumen!C17-Resumen!D17,"#,##0.00") -> S/ 2,454.00 | H6: =TEXT(Resumen!E17,"0.0%") -> 4.1%
